[{"TPDOCUM":"CCF","NNUMDOC":"712","NUMLINHA":"1","TPLINHA":"1","ARTIGO":"374000","DESCR":"GEST\u00c3O REDES SOCIAS + ADS FACEBOOK","PRUNIT":"410","ENCARGOS":"0","QUANT":"1","VALOR":"410.0000","TXDESC":".0000","DESCONTO":"0","IVA":"23.0000","SERIE":"1","VLMOVORI":".0000","QTDORIG":"1.0000","ANO":"2022","RUBRICA":"374000","VLMOVSTK":".0000","DESCVAL":".0000","MOVSTC":"0","SECTOR":"ANS","ARMAZEM":"","DATA":"2022-09-05 00:00:00.000","ORANO":"0","ORDOC":"","ORSERIE":"","ORNUM":"0","ORLIN":"0","UNIDADE":"","FACTOR":"1.0000","LINANU":"0","TPOPER":"1","DESCVO":".0000","VALORO":"410.0000","FORMUL":"0","CODLOT":"","ORDENACA":"1","LINHAREL":"0","DESCRRTF":"","ORDGER":"0","IMPRIME":"0","IDLINDOC":"48357","OPERNEW":"MICKAEL","DATENEW":"2022-10-26 00:00:00.000","HOURNEW":"12:15:01","PROCNEW":"20","OPERUPD":"MICKAEL","DATEUPD":"2022-10-26 00:00:00.000","HOURUPD":"12:15:01","PROCUPD":"20","SIGNATUR":"33774EB98FFF41CDC2562462C0896645","INCOER":"0","ARTIGEAN":"","QTDRES":".0000","QTDRESOR":".0000","RESERVA_OBRA":"","VALOR_SAIDA_STOCK":".0000","VALOR_RETENCAO":".0000","TAXA_RETENCAO":".0000","CATEGORIA_RETENCAO":"0","MOVIMENTA_SO_VALOR":"0","VENDEDOR":"","N_PRECO_LINHA_INTRODUZIDO":"410","N_VALOR_LINHA_INTRODUZIDO":"410.0000","N_TIPO_IVA":"4","N_IVA_LINHA":"94.3000","N_VALOR_TOTAL_DESCONTO":".0000","SERIE_ORIGINAL":"","NUMERO_ORIGINAL":"0","IMPOSTO_ALCOOL":".0000","ECOREEE":".0000","ECOEMBAL":".0000","ECOPILHA":".0000","ECOPNEU":".0000","ECOOUTRO":".0000","VLINTROR":"410.0000","VLIVAOR":"94.3000","VLTOTDESCOR":".0000","LINHAARRED":"0","MOTIVOISENCAOSAFT":"","QUANTIDADE_RETIFICADA":".0000","LINHA_RETIFICADA":"0","NUMERO_AUTORIZACAO":"","VERSAOCATALOGOS":"","CCUSTO":"","PROCESSO_ITEM":"","PROJETO":""},{"TPDOCUM":"CCF","NNUMDOC":"716","NUMLINHA":"1","TPLINHA":"1","ARTIGO":"374000","DESCR":"TRANSPORTE","PRUNIT":"545","ENCARGOS":"0","QUANT":"1","VALOR":"545.0000","TXDESC":".0000","DESCONTO":"0","IVA":".0000","SERIE":"1","VLMOVORI":".0000","QTDORIG":"1.0000","ANO":"2022","RUBRICA":"374000","VLMOVSTK":".0000","DESCVAL":".0000","MOVSTC":"0","SECTOR":"ANS","ARMAZEM":"","DATA":"2022-09-21 00:00:00.000","ORANO":"0","ORDOC":"","ORSERIE":"","ORNUM":"0","ORLIN":"0","UNIDADE":"","FACTOR":"1.0000","LINANU":"0","TPOPER":"1","DESCVO":".0000","VALORO":"545.0000","FORMUL":"0","CODLOT":"","ORDENACA":"1","LINHAREL":"0","DESCRRTF":"","ORDGER":"0","IMPRIME":"0","IDLINDOC":"48372","OPERNEW":"MICKAEL","DATENEW":"2022-10-26 00:00:00.000","HOURNEW":"15:36:04","PROCNEW":"20","OPERUPD":"MICKAEL","DATEUPD":"2022-10-26 00:00:00.000","HOURUPD":"15:36:04","PROCUPD":"20","SIGNATUR":"B8455D3874EBCD55839819305FDE42DB","INCOER":"0","ARTIGEAN":"","QTDRES":".0000","QTDRESOR":".0000","RESERVA_OBRA":"","VALOR_SAIDA_STOCK":".0000","VALOR_RETENCAO":".0000","TAXA_RETENCAO":".0000","CATEGORIA_RETENCAO":"0","MOVIMENTA_SO_VALOR":"0","VENDEDOR":"","N_PRECO_LINHA_INTRODUZIDO":"545","N_VALOR_LINHA_INTRODUZIDO":"545.0000","N_TIPO_IVA":"1","N_IVA_LINHA":".0000","N_VALOR_TOTAL_DESCONTO":".0000","SERIE_ORIGINAL":"","NUMERO_ORIGINAL":"0","IMPOSTO_ALCOOL":".0000","ECOREEE":".0000","ECOEMBAL":".0000","ECOPILHA":".0000","ECOPNEU":".0000","ECOOUTRO":".0000","VLINTROR":"545.0000","VLIVAOR":".0000","VLTOTDESCOR":".0000","LINHAARRED":"0","MOTIVOISENCAOSAFT":"M07","QUANTIDADE_RETIFICADA":".0000","LINHA_RETIFICADA":"0","NUMERO_AUTORIZACAO":"","VERSAOCATALOGOS":"","CCUSTO":"","PROCESSO_ITEM":"","PROJETO":""},{"TPDOCUM":"CCF","NNUMDOC":"716","NUMLINHA":"2","TPLINHA":"1","ARTIGO":"374000","DESCR":"FORMALIDADES ADUANEIRAS","PRUNIT":"120","ENCARGOS":"0","QUANT":"1","VALOR":"120.0000","TXDESC":".0000","DESCONTO":"0","IVA":"23.0000","SERIE":"1","VLMOVORI":".0000","QTDORIG":"1.0000","ANO":"2022","RUBRICA":"374000","VLMOVSTK":".0000","DESCVAL":".0000","MOVSTC":"0","SECTOR":"ANS","ARMAZEM":"","DATA":"2022-09-21 00:00:00.000","ORANO":"0","ORDOC":"","ORSERIE":"","ORNUM":"0","ORLIN":"0","UNIDADE":"","FACTOR":"1.0000","LINANU":"0","TPOPER":"1","DESCVO":".0000","VALORO":"120.0000","FORMUL":"0","CODLOT":"","ORDENACA":"2","LINHAREL":"0","DESCRRTF":"","ORDGER":"0","IMPRIME":"0","IDLINDOC":"48373","OPERNEW":"MICKAEL","DATENEW":"2022-10-26 00:00:00.000","HOURNEW":"15:36:04","PROCNEW":"20","OPERUPD":"MICKAEL","DATEUPD":"2022-10-26 00:00:00.000","HOURUPD":"15:36:04","PROCUPD":"20","SIGNATUR":"F770C6F3867F91FEF29737688615898A","INCOER":"0","ARTIGEAN":"","QTDRES":".0000","QTDRESOR":".0000","RESERVA_OBRA":"","VALOR_SAIDA_STOCK":".0000","VALOR_RETENCAO":".0000","TAXA_RETENCAO":".0000","CATEGORIA_RETENCAO":"0","MOVIMENTA_SO_VALOR":"0","VENDEDOR":"","N_PRECO_LINHA_INTRODUZIDO":"120","N_VALOR_LINHA_INTRODUZIDO":"120.0000","N_TIPO_IVA":"4","N_IVA_LINHA":"27.6000","N_VALOR_TOTAL_DESCONTO":".0000","SERIE_ORIGINAL":"","NUMERO_ORIGINAL":"0","IMPOSTO_ALCOOL":".0000","ECOREEE":".0000","ECOEMBAL":".0000","ECOPILHA":".0000","ECOPNEU":".0000","ECOOUTRO":".0000","VLINTROR":"120.0000","VLIVAOR":"27.6000","VLTOTDESCOR":".0000","LINHAARRED":"0","MOTIVOISENCAOSAFT":"","QUANTIDADE_RETIFICADA":".0000","LINHA_RETIFICADA":"0","NUMERO_AUTORIZACAO":"","VERSAOCATALOGOS":"","CCUSTO":"","PROCESSO_ITEM":"","PROJETO":""},{"TPDOCUM":"CCF","NNUMDOC":"717","NUMLINHA":"1","TPLINHA":"1","ARTIGO":"374000","DESCR":"TRANSPORTE","PRUNIT":"390","ENCARGOS":"0","QUANT":"1","VALOR":"390.0000","TXDESC":".0000","DESCONTO":"0","IVA":"23.0000","SERIE":"1","VLMOVORI":".0000","QTDORIG":"1.0000","ANO":"2022","RUBRICA":"374000","VLMOVSTK":".0000","DESCVAL":".0000","MOVSTC":"0","SECTOR":"ANS","ARMAZEM":"","DATA":"2022-09-22 00:00:00.000","ORANO":"0","ORDOC":"","ORSERIE":"","ORNUM":"0","ORLIN":"0","UNIDADE":"","FACTOR":"1.0000","LINANU":"0","TPOPER":"1","DESCVO":".0000","VALORO":"390.0000","FORMUL":"0","CODLOT":"","ORDENACA":"1","LINHAREL":"0","DESCRRTF":"","ORDGER":"0","IMPRIME":"0","IDLINDOC":"48374","OPERNEW":"MICKAEL","DATENEW":"2022-10-26 00:00:00.000","HOURNEW":"15:36:45","PROCNEW":"20","OPERUPD":"MICKAEL","DATEUPD":"2022-10-26 00:00:00.000","HOURUPD":"15:36:45","PROCUPD":"20","SIGNATUR":"F6C9497744459643ED86DA42BF7584CE","INCOER":"0","ARTIGEAN":"","QTDRES":".0000","QTDRESOR":".0000","RESERVA_OBRA":"","VALOR_SAIDA_STOCK":".0000","VALOR_RETENCAO":".0000","TAXA_RETENCAO":".0000","CATEGORIA_RETENCAO":"0","MOVIMENTA_SO_VALOR":"0","VENDEDOR":"","N_PRECO_LINHA_INTRODUZIDO":"390","N_VALOR_LINHA_INTRODUZIDO":"390.0000","N_TIPO_IVA":"4","N_IVA_LINHA":"89.7000","N_VALOR_TOTAL_DESCONTO":".0000","SERIE_ORIGINAL":"","NUMERO_ORIGINAL":"0","IMPOSTO_ALCOOL":".0000","ECOREEE":".0000","ECOEMBAL":".0000","ECOPILHA":".0000","ECOPNEU":".0000","ECOOUTRO":".0000","VLINTROR":"390.0000","VLIVAOR":"89.7000","VLTOTDESCOR":".0000","LINHAARRED":"0","MOTIVOISENCAOSAFT":"","QUANTIDADE_RETIFICADA":".0000","LINHA_RETIFICADA":"0","NUMERO_AUTORIZACAO":"","VERSAOCATALOGOS":"","CCUSTO":"","PROCESSO_ITEM":"","PROJETO":""},{"TPDOCUM":"CCF","NNUMDOC":"708","NUMLINHA":"1","TPLINHA":"1","ARTIGO":"374000","DESCR":"DESPESAS VIAGEM","PRUNIT":"3189.45","ENCARGOS":"0","QUANT":"1","VALOR":"3189.4500","TXDESC":".0000","DESCONTO":"0","IVA":".0000","SERIE":"1","VLMOVORI":".0000","QTDORIG":"1.0000","ANO":"2022","RUBRICA":"374000","VLMOVSTK":".0000","DESCVAL":".0000","MOVSTC":"0","SECTOR":"ANS","ARMAZEM":"","DATA":"2022-09-28 00:00:00.000","ORANO":"0","ORDOC":"","ORSERIE":"","ORNUM":"0","ORLIN":"0","UNIDADE":"","FACTOR":"1.0000","LINANU":"0","TPOPER":"1","DESCVO":".0000","VALORO":"3189.4500","FORMUL":"0","CODLOT":"","ORDENACA":"1","LINHAREL":"0","DESCRRTF":"","ORDGER":"0","IMPRIME":"0","IDLINDOC":"48353","OPERNEW":"MICKAEL","DATENEW":"2022-10-26 00:00:00.000","HOURNEW":"12:05:31","PROCNEW":"20","OPERUPD":"MICKAEL","DATEUPD":"2022-10-26 00:00:00.000","HOURUPD":"12:05:31","PROCUPD":"20","SIGNATUR":"2F62B99977FC4F817A8C0D146DE048F2","INCOER":"0","ARTIGEAN":"","QTDRES":".0000","QTDRESOR":".0000","RESERVA_OBRA":"","VALOR_SAIDA_STOCK":".0000","VALOR_RETENCAO":".0000","TAXA_RETENCAO":".0000","CATEGORIA_RETENCAO":"0","MOVIMENTA_SO_VALOR":"0","VENDEDOR":"","N_PRECO_LINHA_INTRODUZIDO":"3189.45","N_VALOR_LINHA_INTRODUZIDO":"3189.4500","N_TIPO_IVA":"1","N_IVA_LINHA":".0000","N_VALOR_TOTAL_DESCONTO":".0000","SERIE_ORIGINAL":"","NUMERO_ORIGINAL":"0","IMPOSTO_ALCOOL":".0000","ECOREEE":".0000","ECOEMBAL":".0000","ECOPILHA":".0000","ECOPNEU":".0000","ECOOUTRO":".0000","VLINTROR":"3189.4500","VLIVAOR":".0000","VLTOTDESCOR":".0000","LINHAARRED":"0","MOTIVOISENCAOSAFT":"M07","QUANTIDADE_RETIFICADA":".0000","LINHA_RETIFICADA":"0","NUMERO_AUTORIZACAO":"","VERSAOCATALOGOS":"","CCUSTO":"","PROCESSO_ITEM":"","PROJETO":""},{"TPDOCUM":"CCF","NNUMDOC":"707","NUMLINHA":"1","TPLINHA":"1","ARTIGO":"203-10-180-50","DESCR":"ESTENDEDOR AUTOMATICO FOX   H=180","PRUNIT":"30660.5","ENCARGOS":"0","QUANT":"1","VALOR":"30660.5000","TXDESC":".0000","DESCONTO":"0","IVA":".0000","SERIE":"1","VLMOVORI":"30660.5000","QTDORIG":"1.0000","ANO":"2022","RUBRICA":"","VLMOVSTK":"30660.5000","DESCVAL":".0000","MOVSTC":"1","SECTOR":"ANS","ARMAZEM":"001","DATA":"2022-10-12 00:00:00.000","ORANO":"0","ORDOC":"","ORSERIE":"","ORNUM":"0","ORLIN":"0","UNIDADE":"UN","FACTOR":"1.0000","LINANU":"0","TPOPER":"1","DESCVO":".0000","VALORO":"30660.5000","FORMUL":"0","CODLOT":"","ORDENACA":"1","LINHAREL":"0","DESCRRTF":"","ORDGER":"0","IMPRIME":"0","IDLINDOC":"48337","OPERNEW":"MICKAEL","DATENEW":"2022-10-26 00:00:00.000","HOURNEW":"10:51:43","PROCNEW":"20","OPERUPD":"MICKAEL","DATEUPD":"2022-10-26 00:00:00.000","HOURUPD":"10:51:43","PROCUPD":"20","SIGNATUR":"376F19DE63872F968DDF5E71617B3CF6","INCOER":"0","ARTIGEAN":"","QTDRES":".0000","QTDRESOR":".0000","RESERVA_OBRA":"","VALOR_SAIDA_STOCK":".0000","VALOR_RETENCAO":".0000","TAXA_RETENCAO":".0000","CATEGORIA_RETENCAO":"0","MOVIMENTA_SO_VALOR":"0","VENDEDOR":"","N_PRECO_LINHA_INTRODUZIDO":"30660.5","N_VALOR_LINHA_INTRODUZIDO":"30660.5000","N_TIPO_IVA":"1","N_IVA_LINHA":".0000","N_VALOR_TOTAL_DESCONTO":".0000","SERIE_ORIGINAL":"","NUMERO_ORIGINAL":"0","IMPOSTO_ALCOOL":".0000","ECOREEE":".0000","ECOEMBAL":".0000","ECOPILHA":".0000","ECOPNEU":".0000","ECOOUTRO":".0000","VLINTROR":"30660.5000","VLIVAOR":".0000","VLTOTDESCOR":".0000","LINHAARRED":"0","MOTIVOISENCAOSAFT":"M16","QUANTIDADE_RETIFICADA":".0000","LINHA_RETIFICADA":"0","NUMERO_AUTORIZACAO":"","VERSAOCATALOGOS":"","CCUSTO":"","PROCESSO_ITEM":"","PROJETO":""},{"TPDOCUM":"CCF","NNUMDOC":"707","NUMLINHA":"2","TPLINHA":"1","ARTIGO":"","DESCR":"N\u00ba SERIE: M004616","PRUNIT":"0","ENCARGOS":"0","QUANT":"0","VALOR":".0000","TXDESC":".0000","DESCONTO":"0","IVA":".0000","SERIE":"1","VLMOVORI":".0000","QTDORIG":".0000","ANO":"2022","RUBRICA":"","VLMOVSTK":".0000","DESCVAL":".0000","MOVSTC":"0","SECTOR":"ANS","ARMAZEM":"","DATA":"2022-10-12 00:00:00.000","ORANO":"0","ORDOC":"","ORSERIE":"","ORNUM":"0","ORLIN":"0","UNIDADE":"","FACTOR":"1.0000","LINANU":"0","TPOPER":"0","DESCVO":".0000","VALORO":".0000","FORMUL":"0","CODLOT":"","ORDENACA":"2","LINHAREL":"0","DESCRRTF":"","ORDGER":"0","IMPRIME":"0","IDLINDOC":"48338","OPERNEW":"MICKAEL","DATENEW":"2022-10-26 00:00:00.000","HOURNEW":"10:51:43","PROCNEW":"20","OPERUPD":"MICKAEL","DATEUPD":"2022-10-26 00:00:00.000","HOURUPD":"10:51:43","PROCUPD":"20","SIGNATUR":"46D48D8ECC97D1D64EA593BA58E6539F","INCOER":"0","ARTIGEAN":"","QTDRES":".0000","QTDRESOR":".0000","RESERVA_OBRA":"","VALOR_SAIDA_STOCK":".0000","VALOR_RETENCAO":".0000","TAXA_RETENCAO":".0000","CATEGORIA_RETENCAO":"0","MOVIMENTA_SO_VALOR":"0","VENDEDOR":"","N_PRECO_LINHA_INTRODUZIDO":"0","N_VALOR_LINHA_INTRODUZIDO":".0000","N_TIPO_IVA":"1","N_IVA_LINHA":".0000","N_VALOR_TOTAL_DESCONTO":".0000","SERIE_ORIGINAL":"","NUMERO_ORIGINAL":"0","IMPOSTO_ALCOOL":".0000","ECOREEE":".0000","ECOEMBAL":".0000","ECOPILHA":".0000","ECOPNEU":".0000","ECOOUTRO":".0000","VLINTROR":".0000","VLIVAOR":".0000","VLTOTDESCOR":".0000","LINHAARRED":"0","MOTIVOISENCAOSAFT":"","QUANTIDADE_RETIFICADA":".0000","LINHA_RETIFICADA":"0","NUMERO_AUTORIZACAO":"","VERSAOCATALOGOS":"","CCUSTO":"","PROCESSO_ITEM":"","PROJETO":""},{"TPDOCUM":"CCF","NNUMDOC":"715","NUMLINHA":"1","TPLINHA":"1","ARTIGO":"374000","DESCR":"TRANSPORTE MORGAN > FILC","PRUNIT":"1450","ENCARGOS":"0","QUANT":"1","VALOR":"1450.0000","TXDESC":".0000","DESCONTO":"0","IVA":"23.0000","SERIE":"1","VLMOVORI":".0000","QTDORIG":"1.0000","ANO":"2022","RUBRICA":"374000","VLMOVSTK":".0000","DESCVAL":".0000","MOVSTC":"0","SECTOR":"ANS","ARMAZEM":"","DATA":"2022-10-14 00:00:00.000","ORANO":"0","ORDOC":"","ORSERIE":"","ORNUM":"0","ORLIN":"0","UNIDADE":"","FACTOR":"1.0000","LINANU":"0","TPOPER":"1","DESCVO":".0000","VALORO":"1450.0000","FORMUL":"0","CODLOT":"","ORDENACA":"1","LINHAREL":"0","DESCRRTF":"","ORDGER":"0","IMPRIME":"0","IDLINDOC":"48371","OPERNEW":"MICKAEL","DATENEW":"2022-10-26 00:00:00.000","HOURNEW":"15:26:35","PROCNEW":"20","OPERUPD":"MICKAEL","DATEUPD":"2022-10-26 00:00:00.000","HOURUPD":"15:26:35","PROCUPD":"20","SIGNATUR":"9C91F1879B3475E6BD0A11C5F6FEDCC7","INCOER":"0","ARTIGEAN":"","QTDRES":".0000","QTDRESOR":".0000","RESERVA_OBRA":"","VALOR_SAIDA_STOCK":".0000","VALOR_RETENCAO":".0000","TAXA_RETENCAO":".0000","CATEGORIA_RETENCAO":"0","MOVIMENTA_SO_VALOR":"0","VENDEDOR":"","N_PRECO_LINHA_INTRODUZIDO":"1450","N_VALOR_LINHA_INTRODUZIDO":"1450.0000","N_TIPO_IVA":"4","N_IVA_LINHA":"333.5000","N_VALOR_TOTAL_DESCONTO":".0000","SERIE_ORIGINAL":"","NUMERO_ORIGINAL":"0","IMPOSTO_ALCOOL":".0000","ECOREEE":".0000","ECOEMBAL":".0000","ECOPILHA":".0000","ECOPNEU":".0000","ECOOUTRO":".0000","VLINTROR":"1450.0000","VLIVAOR":"333.5000","VLTOTDESCOR":".0000","LINHAARRED":"0","MOTIVOISENCAOSAFT":"","QUANTIDADE_RETIFICADA":".0000","LINHA_RETIFICADA":"0","NUMERO_AUTORIZACAO":"","VERSAOCATALOGOS":"","CCUSTO":"","PROCESSO_ITEM":"","PROJETO":""},{"TPDOCUM":"CCF","NNUMDOC":"709","NUMLINHA":"1","TPLINHA":"1","ARTIGO":"374000","DESCR":"DESPESAS DE VIAGEM","PRUNIT":"4343.78","ENCARGOS":"0","QUANT":"1","VALOR":"4343.7800","TXDESC":".0000","DESCONTO":"0","IVA":".0000","SERIE":"1","VLMOVORI":".0000","QTDORIG":"1.0000","ANO":"2022","RUBRICA":"374000","VLMOVSTK":".0000","DESCVAL":".0000","MOVSTC":"0","SECTOR":"ANS","ARMAZEM":"","DATA":"2022-10-20 00:00:00.000","ORANO":"0","ORDOC":"","ORSERIE":"","ORNUM":"0","ORLIN":"0","UNIDADE":"","FACTOR":"1.0000","LINANU":"0","TPOPER":"1","DESCVO":".0000","VALORO":"4343.7800","FORMUL":"0","CODLOT":"","ORDENACA":"1","LINHAREL":"0","DESCRRTF":"","ORDGER":"0","IMPRIME":"0","IDLINDOC":"48354","OPERNEW":"MICKAEL","DATENEW":"2022-10-26 00:00:00.000","HOURNEW":"12:06:16","PROCNEW":"20","OPERUPD":"MICKAEL","DATEUPD":"2022-10-26 00:00:00.000","HOURUPD":"12:06:16","PROCUPD":"20","SIGNATUR":"E8CF248EF2B370E4AAF0121AAA98F8F1","INCOER":"0","ARTIGEAN":"","QTDRES":".0000","QTDRESOR":".0000","RESERVA_OBRA":"","VALOR_SAIDA_STOCK":".0000","VALOR_RETENCAO":".0000","TAXA_RETENCAO":".0000","CATEGORIA_RETENCAO":"0","MOVIMENTA_SO_VALOR":"0","VENDEDOR":"","N_PRECO_LINHA_INTRODUZIDO":"4343.78","N_VALOR_LINHA_INTRODUZIDO":"4343.7800","N_TIPO_IVA":"1","N_IVA_LINHA":".0000","N_VALOR_TOTAL_DESCONTO":".0000","SERIE_ORIGINAL":"","NUMERO_ORIGINAL":"0","IMPOSTO_ALCOOL":".0000","ECOREEE":".0000","ECOEMBAL":".0000","ECOPILHA":".0000","ECOPNEU":".0000","ECOOUTRO":".0000","VLINTROR":"4343.7800","VLIVAOR":".0000","VLTOTDESCOR":".0000","LINHAARRED":"0","MOTIVOISENCAOSAFT":"M07","QUANTIDADE_RETIFICADA":".0000","LINHA_RETIFICADA":"0","NUMERO_AUTORIZACAO":"","VERSAOCATALOGOS":"","CCUSTO":"","PROCESSO_ITEM":"","PROJETO":""},{"TPDOCUM":"CCF","NNUMDOC":"710","NUMLINHA":"1","TPLINHA":"1","ARTIGO":"374000","DESCR":"DESPESAS DE ALOJAMENTO","PRUNIT":"193","ENCARGOS":"0","QUANT":"1","VALOR":"193.0000","TXDESC":".0000","DESCONTO":"0","IVA":".0000","SERIE":"1","VLMOVORI":".0000","QTDORIG":"1.0000","ANO":"2022","RUBRICA":"374000","VLMOVSTK":".0000","DESCVAL":".0000","MOVSTC":"0","SECTOR":"ANS","ARMAZEM":"","DATA":"2022-10-20 00:00:00.000","ORANO":"0","ORDOC":"","ORSERIE":"","ORNUM":"0","ORLIN":"0","UNIDADE":"","FACTOR":"1.0000","LINANU":"0","TPOPER":"1","DESCVO":".0000","VALORO":"193.0000","FORMUL":"0","CODLOT":"","ORDENACA":"1","LINHAREL":"0","DESCRRTF":"","ORDGER":"0","IMPRIME":"0","IDLINDOC":"48355","OPERNEW":"MICKAEL","DATENEW":"2022-10-26 00:00:00.000","HOURNEW":"12:06:50","PROCNEW":"20","OPERUPD":"MICKAEL","DATEUPD":"2022-10-26 00:00:00.000","HOURUPD":"12:06:50","PROCUPD":"20","SIGNATUR":"6D601E421617BC7D2D1F270FF85F291E","INCOER":"0","ARTIGEAN":"","QTDRES":".0000","QTDRESOR":".0000","RESERVA_OBRA":"","VALOR_SAIDA_STOCK":".0000","VALOR_RETENCAO":".0000","TAXA_RETENCAO":".0000","CATEGORIA_RETENCAO":"0","MOVIMENTA_SO_VALOR":"0","VENDEDOR":"","N_PRECO_LINHA_INTRODUZIDO":"193","N_VALOR_LINHA_INTRODUZIDO":"193.0000","N_TIPO_IVA":"1","N_IVA_LINHA":".0000","N_VALOR_TOTAL_DESCONTO":".0000","SERIE_ORIGINAL":"","NUMERO_ORIGINAL":"0","IMPOSTO_ALCOOL":".0000","ECOREEE":".0000","ECOEMBAL":".0000","ECOPILHA":".0000","ECOPNEU":".0000","ECOOUTRO":".0000","VLINTROR":"193.0000","VLIVAOR":".0000","VLTOTDESCOR":".0000","LINHAARRED":"0","MOTIVOISENCAOSAFT":"M07","QUANTIDADE_RETIFICADA":".0000","LINHA_RETIFICADA":"0","NUMERO_AUTORIZACAO":"","VERSAOCATALOGOS":"","CCUSTO":"","PROCESSO_ITEM":"","PROJETO":""},{"TPDOCUM":"CCF","NNUMDOC":"713","NUMLINHA":"1","TPLINHA":"1","ARTIGO":"204558","DESCR":"PLOTTER TDOT 220 4195\u0080 + 1001\u0080 EM OPCIONAIS","PRUNIT":"5196","ENCARGOS":"0","QUANT":"1","VALOR":"5196.0000","TXDESC":".0000","DESCONTO":"0","IVA":".0000","SERIE":"1","VLMOVORI":"5196.0000","QTDORIG":"1.0000","ANO":"2022","RUBRICA":"","VLMOVSTK":"5196.0000","DESCVAL":".0000","MOVSTC":"1","SECTOR":"ANS","ARMAZEM":"001","DATA":"2022-10-20 00:00:00.000","ORANO":"0","ORDOC":"","ORSERIE":"","ORNUM":"0","ORLIN":"0","UNIDADE":"UN","FACTOR":"1.0000","LINANU":"0","TPOPER":"1","DESCVO":".0000","VALORO":"5196.0000","FORMUL":"0","CODLOT":"","ORDENACA":"1","LINHAREL":"0","DESCRRTF":"","ORDGER":"0","IMPRIME":"0","IDLINDOC":"48359","OPERNEW":"MICKAEL","DATENEW":"2022-10-26 00:00:00.000","HOURNEW":"13:33:49","PROCNEW":"20","OPERUPD":"MICKAEL","DATEUPD":"2022-10-26 00:00:00.000","HOURUPD":"13:33:49","PROCUPD":"20","SIGNATUR":"93CAAA25CDEB3623F008EB05DC474390","INCOER":"0","ARTIGEAN":"","QTDRES":".0000","QTDRESOR":".0000","RESERVA_OBRA":"","VALOR_SAIDA_STOCK":".0000","VALOR_RETENCAO":".0000","TAXA_RETENCAO":".0000","CATEGORIA_RETENCAO":"0","MOVIMENTA_SO_VALOR":"0","VENDEDOR":"","N_PRECO_LINHA_INTRODUZIDO":"5196","N_VALOR_LINHA_INTRODUZIDO":"5196.0000","N_TIPO_IVA":"1","N_IVA_LINHA":".0000","N_VALOR_TOTAL_DESCONTO":".0000","SERIE_ORIGINAL":"","NUMERO_ORIGINAL":"0","IMPOSTO_ALCOOL":".0000","ECOREEE":".0000","ECOEMBAL":".0000","ECOPILHA":".0000","ECOPNEU":".0000","ECOOUTRO":".0000","VLINTROR":"5196.0000","VLIVAOR":".0000","VLTOTDESCOR":".0000","LINHAARRED":"0","MOTIVOISENCAOSAFT":"M16","QUANTIDADE_RETIFICADA":".0000","LINHA_RETIFICADA":"0","NUMERO_AUTORIZACAO":"","VERSAOCATALOGOS":"","CCUSTO":"","PROCESSO_ITEM":"","PROJETO":""},{"TPDOCUM":"CCF","NNUMDOC":"713","NUMLINHA":"2","TPLINHA":"1","ARTIGO":"","DESCR":"N\u00ba SERIE: 8BI5L","PRUNIT":"0","ENCARGOS":"0","QUANT":"0","VALOR":".0000","TXDESC":".0000","DESCONTO":"0","IVA":".0000","SERIE":"1","VLMOVORI":".0000","QTDORIG":".0000","ANO":"2022","RUBRICA":"","VLMOVSTK":".0000","DESCVAL":".0000","MOVSTC":"0","SECTOR":"ANS","ARMAZEM":"","DATA":"2022-10-20 00:00:00.000","ORANO":"0","ORDOC":"","ORSERIE":"","ORNUM":"0","ORLIN":"0","UNIDADE":"","FACTOR":"1.0000","LINANU":"0","TPOPER":"0","DESCVO":".0000","VALORO":".0000","FORMUL":"0","CODLOT":"","ORDENACA":"2","LINHAREL":"0","DESCRRTF":"","ORDGER":"0","IMPRIME":"0","IDLINDOC":"48360","OPERNEW":"MICKAEL","DATENEW":"2022-10-26 00:00:00.000","HOURNEW":"13:33:49","PROCNEW":"20","OPERUPD":"MICKAEL","DATEUPD":"2022-10-26 00:00:00.000","HOURUPD":"13:33:49","PROCUPD":"20","SIGNATUR":"1185F931324DA1ECA24AEAFBEBB95043","INCOER":"0","ARTIGEAN":"","QTDRES":".0000","QTDRESOR":".0000","RESERVA_OBRA":"","VALOR_SAIDA_STOCK":".0000","VALOR_RETENCAO":".0000","TAXA_RETENCAO":".0000","CATEGORIA_RETENCAO":"0","MOVIMENTA_SO_VALOR":"0","VENDEDOR":"","N_PRECO_LINHA_INTRODUZIDO":"0","N_VALOR_LINHA_INTRODUZIDO":".0000","N_TIPO_IVA":"1","N_IVA_LINHA":".0000","N_VALOR_TOTAL_DESCONTO":".0000","SERIE_ORIGINAL":"","NUMERO_ORIGINAL":"0","IMPOSTO_ALCOOL":".0000","ECOREEE":".0000","ECOEMBAL":".0000","ECOPILHA":".0000","ECOPNEU":".0000","ECOOUTRO":".0000","VLINTROR":".0000","VLIVAOR":".0000","VLTOTDESCOR":".0000","LINHAARRED":"0","MOTIVOISENCAOSAFT":"","QUANTIDADE_RETIFICADA":".0000","LINHA_RETIFICADA":"0","NUMERO_AUTORIZACAO":"","VERSAOCATALOGOS":"","CCUSTO":"","PROCESSO_ITEM":"","PROJETO":""},{"TPDOCUM":"CCF","NNUMDOC":"711","NUMLINHA":"1","TPLINHA":"1","ARTIGO":"374000","DESCR":"AVEN\u00c7A DE CONTABILIDADE DE OUTUBRO DE 2022","PRUNIT":"425","ENCARGOS":"0","QUANT":"1","VALOR":"425.0000","TXDESC":".0000","DESCONTO":"0","IVA":"23.0000","SERIE":"1","VLMOVORI":".0000","QTDORIG":"1.0000","ANO":"2022","RUBRICA":"374000","VLMOVSTK":".0000","DESCVAL":".0000","MOVSTC":"0","SECTOR":"ANS","ARMAZEM":"","DATA":"2022-10-21 00:00:00.000","ORANO":"0","ORDOC":"","ORSERIE":"","ORNUM":"0","ORLIN":"0","UNIDADE":"","FACTOR":"1.0000","LINANU":"0","TPOPER":"1","DESCVO":".0000","VALORO":"425.0000","FORMUL":"0","CODLOT":"","ORDENACA":"1","LINHAREL":"0","DESCRRTF":"","ORDGER":"0","IMPRIME":"0","IDLINDOC":"48356","OPERNEW":"MICKAEL","DATENEW":"2022-10-26 00:00:00.000","HOURNEW":"12:09:52","PROCNEW":"20","OPERUPD":"MICKAEL","DATEUPD":"2022-10-26 00:00:00.000","HOURUPD":"12:09:52","PROCUPD":"20","SIGNATUR":"4AEDDC77896BEEF76BFB865BB1A9FFF1","INCOER":"0","ARTIGEAN":"","QTDRES":".0000","QTDRESOR":".0000","RESERVA_OBRA":"","VALOR_SAIDA_STOCK":".0000","VALOR_RETENCAO":".0000","TAXA_RETENCAO":".0000","CATEGORIA_RETENCAO":"0","MOVIMENTA_SO_VALOR":"0","VENDEDOR":"","N_PRECO_LINHA_INTRODUZIDO":"425","N_VALOR_LINHA_INTRODUZIDO":"425.0000","N_TIPO_IVA":"4","N_IVA_LINHA":"97.7500","N_VALOR_TOTAL_DESCONTO":".0000","SERIE_ORIGINAL":"","NUMERO_ORIGINAL":"0","IMPOSTO_ALCOOL":".0000","ECOREEE":".0000","ECOEMBAL":".0000","ECOPILHA":".0000","ECOPNEU":".0000","ECOOUTRO":".0000","VLINTROR":"425.0000","VLIVAOR":"97.7500","VLTOTDESCOR":".0000","LINHAARRED":"0","MOTIVOISENCAOSAFT":"","QUANTIDADE_RETIFICADA":".0000","LINHA_RETIFICADA":"0","NUMERO_AUTORIZACAO":"","VERSAOCATALOGOS":"","CCUSTO":"","PROCESSO_ITEM":"","PROJETO":""},{"TPDOCUM":"CCF","NNUMDOC":"714","NUMLINHA":"1","TPLINHA":"1","ARTIGO":"374000","DESCR":"GASOLEO","PRUNIT":"551.72","ENCARGOS":"0","QUANT":"1","VALOR":"551.7200","TXDESC":".0000","DESCONTO":"0","IVA":"23.0000","SERIE":"1","VLMOVORI":".0000","QTDORIG":"1.0000","ANO":"2022","RUBRICA":"374000","VLMOVSTK":".0000","DESCVAL":".0000","MOVSTC":"0","SECTOR":"ANS","ARMAZEM":"","DATA":"2022-10-23 00:00:00.000","ORANO":"0","ORDOC":"","ORSERIE":"","ORNUM":"0","ORLIN":"0","UNIDADE":"","FACTOR":"1.0000","LINANU":"0","TPOPER":"1","DESCVO":".0000","VALORO":"551.7200","FORMUL":"0","CODLOT":"","ORDENACA":"1","LINHAREL":"0","DESCRRTF":"","ORDGER":"0","IMPRIME":"0","IDLINDOC":"48361","OPERNEW":"MICKAEL","DATENEW":"2022-10-26 00:00:00.000","HOURNEW":"13:38:29","PROCNEW":"20","OPERUPD":"MICKAEL","DATEUPD":"2022-10-26 00:00:00.000","HOURUPD":"13:38:29","PROCUPD":"20","SIGNATUR":"BDBF694230DCC30E22C524A011024B32","INCOER":"0","ARTIGEAN":"","QTDRES":".0000","QTDRESOR":".0000","RESERVA_OBRA":"","VALOR_SAIDA_STOCK":".0000","VALOR_RETENCAO":".0000","TAXA_RETENCAO":".0000","CATEGORIA_RETENCAO":"0","MOVIMENTA_SO_VALOR":"0","VENDEDOR":"","N_PRECO_LINHA_INTRODUZIDO":"551.72","N_VALOR_LINHA_INTRODUZIDO":"551.7200","N_TIPO_IVA":"4","N_IVA_LINHA":"126.8956","N_VALOR_TOTAL_DESCONTO":".0000","SERIE_ORIGINAL":"","NUMERO_ORIGINAL":"0","IMPOSTO_ALCOOL":".0000","ECOREEE":".0000","ECOEMBAL":".0000","ECOPILHA":".0000","ECOPNEU":".0000","ECOOUTRO":".0000","VLINTROR":"551.7200","VLIVAOR":"126.8956","VLTOTDESCOR":".0000","LINHAARRED":"0","MOTIVOISENCAOSAFT":"","QUANTIDADE_RETIFICADA":".0000","LINHA_RETIFICADA":"0","NUMERO_AUTORIZACAO":"","VERSAOCATALOGOS":"","CCUSTO":"","PROCESSO_ITEM":"","PROJETO":""},{"TPDOCUM":"CPR","NNUMDOC":"8","NUMLINHA":"1","TPLINHA":"1","ARTIGO":"3516","DESCR":"CADEIRA PLASTICA GAS 1600G","PRUNIT":"36.1661","ENCARGOS":"0","QUANT":"1","VALOR":"36.1661","TXDESC":".0000","DESCONTO":"","IVA":".0000","SERIE":"9","VLMOVORI":"36.1661","QTDORIG":"1.0000","ANO":"2022","RUBRICA":"","VLMOVSTK":"36.1661","DESCVAL":".0000","MOVSTC":"2","SECTOR":"ANS","ARMAZEM":"001","DATA":"2022-10-26 00:00:00.000","ORANO":"0","ORDOC":"","ORSERIE":"","ORNUM":"0","ORLIN":"0","UNIDADE":"UN","FACTOR":"1.0000","LINANU":"0","TPOPER":"2","DESCVO":".0000","VALORO":"36.1661","FORMUL":"0","CODLOT":"","ORDENACA":"0","LINHAREL":"0","DESCRRTF":"","ORDGER":"0","IMPRIME":"0","IDLINDOC":"48332","OPERNEW":"MICKAEL","DATENEW":"2022-10-26 00:00:00.000","HOURNEW":"09:00:29","PROCNEW":"30","OPERUPD":"MICKAEL","DATEUPD":"2022-10-26 00:00:00.000","HOURUPD":"09:00:29","PROCUPD":"30","SIGNATUR":"","INCOER":"0","ARTIGEAN":"","QTDRES":".0000","QTDRESOR":".0000","RESERVA_OBRA":"","VALOR_SAIDA_STOCK":".0000","VALOR_RETENCAO":".0000","TAXA_RETENCAO":".0000","CATEGORIA_RETENCAO":"0","MOVIMENTA_SO_VALOR":"0","VENDEDOR":"","N_PRECO_LINHA_INTRODUZIDO":"0","N_VALOR_LINHA_INTRODUZIDO":".0000","N_TIPO_IVA":"0","N_IVA_LINHA":".0000","N_VALOR_TOTAL_DESCONTO":".0000","SERIE_ORIGINAL":"","NUMERO_ORIGINAL":"0","IMPOSTO_ALCOOL":".0000","ECOREEE":".0000","ECOEMBAL":".0000","ECOPILHA":".0000","ECOPNEU":".0000","ECOOUTRO":".0000","VLINTROR":".0000","VLIVAOR":".0000","VLTOTDESCOR":".0000","LINHAARRED":"0","MOTIVOISENCAOSAFT":"","QUANTIDADE_RETIFICADA":".0000","LINHA_RETIFICADA":"0","NUMERO_AUTORIZACAO":"","VERSAOCATALOGOS":"","CCUSTO":"","PROCESSO_ITEM":"","PROJETO":""},{"TPDOCUM":"FM","NNUMDOC":"113","NUMLINHA":"1","TPLINHA":"1","ARTIGO":"203-10-180-50","DESCR":"CARRO DE ESTENDER FOX 50 L=180CM","PRUNIT":"47000","ENCARGOS":"0","QUANT":"1","VALOR":"47000.0000","TXDESC":".0000","DESCONTO":"0","IVA":"23.0000","SERIE":"22","VLMOVORI":"30660.5000","QTDORIG":"1.0000","ANO":"2022","RUBRICA":"","VLMOVSTK":"30660.5000","DESCVAL":".0000","MOVSTC":"2","SECTOR":"ANS","ARMAZEM":"001","DATA":"2022-10-26 00:00:00.000","ORANO":"0","ORDOC":"","ORSERIE":"","ORNUM":"0","ORLIN":"0","UNIDADE":"UN","FACTOR":"1.0000","LINANU":"0","TPOPER":"2","DESCVO":".0000","VALORO":"47000.0000","FORMUL":"0","CODLOT":"","ORDENACA":"1","LINHAREL":"0","DESCRRTF":"","ORDGER":"0","IMPRIME":"0","IDLINDOC":"48339","OPERNEW":"MICKAEL","DATENEW":"2022-10-26 00:00:00.000","HOURNEW":"10:53:39","PROCNEW":"1","OPERUPD":"MICKAEL","DATEUPD":"2022-10-26 00:00:00.000","HOURUPD":"10:53:39","PROCUPD":"1","SIGNATUR":"48AE9E802B74B144B4153933A5D0705F","INCOER":"0","ARTIGEAN":"","QTDRES":".0000","QTDRESOR":".0000","RESERVA_OBRA":"","VALOR_SAIDA_STOCK":".0000","VALOR_RETENCAO":".0000","TAXA_RETENCAO":".0000","CATEGORIA_RETENCAO":"0","MOVIMENTA_SO_VALOR":"0","VENDEDOR":"Gen","N_PRECO_LINHA_INTRODUZIDO":"47000","N_VALOR_LINHA_INTRODUZIDO":"47000.0000","N_TIPO_IVA":"4","N_IVA_LINHA":"10810.0000","N_VALOR_TOTAL_DESCONTO":".0000","SERIE_ORIGINAL":"","NUMERO_ORIGINAL":"0","IMPOSTO_ALCOOL":".0000","ECOREEE":".0000","ECOEMBAL":".0000","ECOPILHA":".0000","ECOPNEU":".0000","ECOOUTRO":".0000","VLINTROR":"47000.0000","VLIVAOR":"10810.0000","VLTOTDESCOR":".0000","LINHAARRED":"0","MOTIVOISENCAOSAFT":"","QUANTIDADE_RETIFICADA":".0000","LINHA_RETIFICADA":"0","NUMERO_AUTORIZACAO":"","VERSAOCATALOGOS":"","CCUSTO":"","PROCESSO_ITEM":"","PROJETO":""},{"TPDOCUM":"FM","NNUMDOC":"113","NUMLINHA":"2","TPLINHA":"1","ARTIGO":"","DESCR":"EQUIPADO C\/ BARRA ANTI-ESTATICA","PRUNIT":"0","ENCARGOS":"0","QUANT":"0","VALOR":".0000","TXDESC":".0000","DESCONTO":"0","IVA":".0000","SERIE":"22","VLMOVORI":".0000","QTDORIG":".0000","ANO":"2022","RUBRICA":"","VLMOVSTK":".0000","DESCVAL":".0000","MOVSTC":"0","SECTOR":"ANS","ARMAZEM":"","DATA":"2022-10-26 00:00:00.000","ORANO":"0","ORDOC":"","ORSERIE":"","ORNUM":"0","ORLIN":"0","UNIDADE":"","FACTOR":"1.0000","LINANU":"0","TPOPER":"0","DESCVO":".0000","VALORO":".0000","FORMUL":"0","CODLOT":"","ORDENACA":"3","LINHAREL":"0","DESCRRTF":"","ORDGER":"0","IMPRIME":"0","IDLINDOC":"48340","OPERNEW":"MICKAEL","DATENEW":"2022-10-26 00:00:00.000","HOURNEW":"10:53:39","PROCNEW":"1","OPERUPD":"MICKAEL","DATEUPD":"2022-10-26 00:00:00.000","HOURUPD":"10:53:39","PROCUPD":"1","SIGNATUR":"D1A80CCBF9C90F48D451DA6BB3FABBAC","INCOER":"0","ARTIGEAN":"","QTDRES":".0000","QTDRESOR":".0000","RESERVA_OBRA":"","VALOR_SAIDA_STOCK":".0000","VALOR_RETENCAO":".0000","TAXA_RETENCAO":".0000","CATEGORIA_RETENCAO":"0","MOVIMENTA_SO_VALOR":"0","VENDEDOR":"Gen","N_PRECO_LINHA_INTRODUZIDO":"0","N_VALOR_LINHA_INTRODUZIDO":".0000","N_TIPO_IVA":"1","N_IVA_LINHA":".0000","N_VALOR_TOTAL_DESCONTO":".0000","SERIE_ORIGINAL":"","NUMERO_ORIGINAL":"0","IMPOSTO_ALCOOL":".0000","ECOREEE":".0000","ECOEMBAL":".0000","ECOPILHA":".0000","ECOPNEU":".0000","ECOOUTRO":".0000","VLINTROR":".0000","VLIVAOR":".0000","VLTOTDESCOR":".0000","LINHAARRED":"0","MOTIVOISENCAOSAFT":"","QUANTIDADE_RETIFICADA":".0000","LINHA_RETIFICADA":"0","NUMERO_AUTORIZACAO":"","VERSAOCATALOGOS":"","CCUSTO":"","PROCESSO_ITEM":"","PROJETO":""},{"TPDOCUM":"FM","NNUMDOC":"113","NUMLINHA":"3","TPLINHA":"1","ARTIGO":"","DESCR":"SISTEMA DE PIN\u00c7AS MOVEL","PRUNIT":"0","ENCARGOS":"0","QUANT":"0","VALOR":".0000","TXDESC":".0000","DESCONTO":"0","IVA":".0000","SERIE":"22","VLMOVORI":".0000","QTDORIG":".0000","ANO":"2022","RUBRICA":"","VLMOVSTK":".0000","DESCVAL":".0000","MOVSTC":"0","SECTOR":"ANS","ARMAZEM":"","DATA":"2022-10-26 00:00:00.000","ORANO":"0","ORDOC":"","ORSERIE":"","ORNUM":"0","ORLIN":"0","UNIDADE":"","FACTOR":"1.0000","LINANU":"0","TPOPER":"0","DESCVO":".0000","VALORO":".0000","FORMUL":"0","CODLOT":"","ORDENACA":"4","LINHAREL":"0","DESCRRTF":"","ORDGER":"0","IMPRIME":"0","IDLINDOC":"48341","OPERNEW":"MICKAEL","DATENEW":"2022-10-26 00:00:00.000","HOURNEW":"10:53:39","PROCNEW":"1","OPERUPD":"MICKAEL","DATEUPD":"2022-10-26 00:00:00.000","HOURUPD":"10:53:39","PROCUPD":"1","SIGNATUR":"C066AF54A4E3B0FF93469F5C9C3AFB75","INCOER":"0","ARTIGEAN":"","QTDRES":".0000","QTDRESOR":".0000","RESERVA_OBRA":"","VALOR_SAIDA_STOCK":".0000","VALOR_RETENCAO":".0000","TAXA_RETENCAO":".0000","CATEGORIA_RETENCAO":"0","MOVIMENTA_SO_VALOR":"0","VENDEDOR":"Gen","N_PRECO_LINHA_INTRODUZIDO":"0","N_VALOR_LINHA_INTRODUZIDO":".0000","N_TIPO_IVA":"1","N_IVA_LINHA":".0000","N_VALOR_TOTAL_DESCONTO":".0000","SERIE_ORIGINAL":"","NUMERO_ORIGINAL":"0","IMPOSTO_ALCOOL":".0000","ECOREEE":".0000","ECOEMBAL":".0000","ECOPILHA":".0000","ECOPNEU":".0000","ECOOUTRO":".0000","VLINTROR":".0000","VLIVAOR":".0000","VLTOTDESCOR":".0000","LINHAARRED":"0","MOTIVOISENCAOSAFT":"","QUANTIDADE_RETIFICADA":".0000","LINHA_RETIFICADA":"0","NUMERO_AUTORIZACAO":"","VERSAOCATALOGOS":"","CCUSTO":"","PROCESSO_ITEM":"","PROJETO":""},{"TPDOCUM":"FM","NNUMDOC":"113","NUMLINHA":"4","TPLINHA":"1","ARTIGO":"","DESCR":"14MT MESA C\/ INSUFLA\u00c7\u00c3O","PRUNIT":"0","ENCARGOS":"0","QUANT":"0","VALOR":".0000","TXDESC":".0000","DESCONTO":"0","IVA":".0000","SERIE":"22","VLMOVORI":".0000","QTDORIG":".0000","ANO":"2022","RUBRICA":"","VLMOVSTK":".0000","DESCVAL":".0000","MOVSTC":"0","SECTOR":"ANS","ARMAZEM":"","DATA":"2022-10-26 00:00:00.000","ORANO":"0","ORDOC":"","ORSERIE":"","ORNUM":"0","ORLIN":"0","UNIDADE":"","FACTOR":"1.0000","LINANU":"0","TPOPER":"0","DESCVO":".0000","VALORO":".0000","FORMUL":"0","CODLOT":"","ORDENACA":"5","LINHAREL":"0","DESCRRTF":"","ORDGER":"0","IMPRIME":"0","IDLINDOC":"48342","OPERNEW":"MICKAEL","DATENEW":"2022-10-26 00:00:00.000","HOURNEW":"10:53:39","PROCNEW":"1","OPERUPD":"MICKAEL","DATEUPD":"2022-10-26 00:00:00.000","HOURUPD":"10:53:39","PROCUPD":"1","SIGNATUR":"2667676909DA88BD9DFC6D71BC32B00B","INCOER":"0","ARTIGEAN":"","QTDRES":".0000","QTDRESOR":".0000","RESERVA_OBRA":"","VALOR_SAIDA_STOCK":".0000","VALOR_RETENCAO":".0000","TAXA_RETENCAO":".0000","CATEGORIA_RETENCAO":"0","MOVIMENTA_SO_VALOR":"0","VENDEDOR":"Gen","N_PRECO_LINHA_INTRODUZIDO":"0","N_VALOR_LINHA_INTRODUZIDO":".0000","N_TIPO_IVA":"1","N_IVA_LINHA":".0000","N_VALOR_TOTAL_DESCONTO":".0000","SERIE_ORIGINAL":"","NUMERO_ORIGINAL":"0","IMPOSTO_ALCOOL":".0000","ECOREEE":".0000","ECOEMBAL":".0000","ECOPILHA":".0000","ECOPNEU":".0000","ECOOUTRO":".0000","VLINTROR":".0000","VLIVAOR":".0000","VLTOTDESCOR":".0000","LINHAARRED":"0","MOTIVOISENCAOSAFT":"","QUANTIDADE_RETIFICADA":".0000","LINHA_RETIFICADA":"0","NUMERO_AUTORIZACAO":"","VERSAOCATALOGOS":"","CCUSTO":"","PROCESSO_ITEM":"","PROJETO":""},{"TPDOCUM":"FM","NNUMDOC":"113","NUMLINHA":"6","TPLINHA":"1","ARTIGO":"","DESCR":"N\u00ba SERIE: M004616","PRUNIT":"0","ENCARGOS":"0","QUANT":"0","VALOR":".0000","TXDESC":".0000","DESCONTO":"0","IVA":".0000","SERIE":"22","VLMOVORI":".0000","QTDORIG":".0000","ANO":"2022","RUBRICA":"","VLMOVSTK":".0000","DESCVAL":".0000","MOVSTC":"0","SECTOR":"ANS","ARMAZEM":"","DATA":"2022-10-26 00:00:00.000","ORANO":"0","ORDOC":"","ORSERIE":"","ORNUM":"0","ORLIN":"0","UNIDADE":"","FACTOR":"1.0000","LINANU":"0","TPOPER":"0","DESCVO":".0000","VALORO":".0000","FORMUL":"0","CODLOT":"","ORDENACA":"2","LINHAREL":"0","DESCRRTF":"","ORDGER":"0","IMPRIME":"0","IDLINDOC":"48343","OPERNEW":"MICKAEL","DATENEW":"2022-10-26 00:00:00.000","HOURNEW":"10:53:39","PROCNEW":"1","OPERUPD":"MICKAEL","DATEUPD":"2022-10-26 00:00:00.000","HOURUPD":"10:53:39","PROCUPD":"1","SIGNATUR":"18EB049BF5FF064B2C1C801A624134CC","INCOER":"0","ARTIGEAN":"","QTDRES":".0000","QTDRESOR":".0000","RESERVA_OBRA":"","VALOR_SAIDA_STOCK":".0000","VALOR_RETENCAO":".0000","TAXA_RETENCAO":".0000","CATEGORIA_RETENCAO":"0","MOVIMENTA_SO_VALOR":"0","VENDEDOR":"Gen","N_PRECO_LINHA_INTRODUZIDO":"0","N_VALOR_LINHA_INTRODUZIDO":".0000","N_TIPO_IVA":"1","N_IVA_LINHA":".0000","N_VALOR_TOTAL_DESCONTO":".0000","SERIE_ORIGINAL":"","NUMERO_ORIGINAL":"0","IMPOSTO_ALCOOL":".0000","ECOREEE":".0000","ECOEMBAL":".0000","ECOPILHA":".0000","ECOPNEU":".0000","ECOOUTRO":".0000","VLINTROR":".0000","VLIVAOR":".0000","VLTOTDESCOR":".0000","LINHAARRED":"0","MOTIVOISENCAOSAFT":"","QUANTIDADE_RETIFICADA":".0000","LINHA_RETIFICADA":"0","NUMERO_AUTORIZACAO":"","VERSAOCATALOGOS":"","CCUSTO":"","PROCESSO_ITEM":"","PROJETO":""},{"TPDOCUM":"FS","NNUMDOC":"205","NUMLINHA":"1","TPLINHA":"1","ARTIGO":"DSC","DESCR":"CONTRATO DE 40H SERVI\u00c7O COSTURA","PRUNIT":"1200","ENCARGOS":"0","QUANT":"1","VALOR":"1200.0000","TXDESC":".0000","DESCONTO":"0","IVA":"23.0000","SERIE":"22","VLMOVORI":".0000","QTDORIG":"1.0000","ANO":"2022","RUBRICA":"DSC","VLMOVSTK":".0000","DESCVAL":".0000","MOVSTC":"0","SECTOR":"ANS","ARMAZEM":"","DATA":"2022-10-26 00:00:00.000","ORANO":"0","ORDOC":"","ORSERIE":"","ORNUM":"0","ORLIN":"0","UNIDADE":"","FACTOR":"1.0000","LINANU":"0","TPOPER":"2","DESCVO":".0000","VALORO":"1200.0000","FORMUL":"0","CODLOT":"","ORDENACA":"1","LINHAREL":"0","DESCRRTF":"","ORDGER":"0","IMPRIME":"0","IDLINDOC":"48344","OPERNEW":"MICKAEL","DATENEW":"2022-10-26 00:00:00.000","HOURNEW":"11:02:18","PROCNEW":"1","OPERUPD":"MICKAEL","DATEUPD":"2022-10-26 00:00:00.000","HOURUPD":"11:02:18","PROCUPD":"1","SIGNATUR":"8D4641A48D1AADDB903F4F2AC070DF96","INCOER":"0","ARTIGEAN":"","QTDRES":".0000","QTDRESOR":".0000","RESERVA_OBRA":"","VALOR_SAIDA_STOCK":".0000","VALOR_RETENCAO":".0000","TAXA_RETENCAO":".0000","CATEGORIA_RETENCAO":"0","MOVIMENTA_SO_VALOR":"0","VENDEDOR":"RES","N_PRECO_LINHA_INTRODUZIDO":"1200","N_VALOR_LINHA_INTRODUZIDO":"1200.0000","N_TIPO_IVA":"4","N_IVA_LINHA":"276.0000","N_VALOR_TOTAL_DESCONTO":".0000","SERIE_ORIGINAL":"","NUMERO_ORIGINAL":"0","IMPOSTO_ALCOOL":".0000","ECOREEE":".0000","ECOEMBAL":".0000","ECOPILHA":".0000","ECOPNEU":".0000","ECOOUTRO":".0000","VLINTROR":"1200.0000","VLIVAOR":"276.0000","VLTOTDESCOR":".0000","LINHAARRED":"0","MOTIVOISENCAOSAFT":"","QUANTIDADE_RETIFICADA":".0000","LINHA_RETIFICADA":"0","NUMERO_AUTORIZACAO":"","VERSAOCATALOGOS":"","CCUSTO":"","PROCESSO_ITEM":"","PROJETO":""},{"TPDOCUM":"FTP","NNUMDOC":"412","NUMLINHA":"1","TPLINHA":"1","ARTIGO":"508-16-121","DESCR":"LIXAS P\/MAQ.CORTE AUTOMATICO NEXT 2","PRUNIT":"1.4","ENCARGOS":"0","QUANT":"60","VALOR":"84.0000","TXDESC":".0000","DESCONTO":"0","IVA":"23.0000","SERIE":"22","VLMOVORI":"33.9498","QTDORIG":"60.0000","ANO":"2022","RUBRICA":"","VLMOVSTK":"33.9498","DESCVAL":".0000","MOVSTC":"2","SECTOR":"ANS","ARMAZEM":"001","DATA":"2022-10-26 00:00:00.000","ORANO":"0","ORDOC":"","ORSERIE":"","ORNUM":"0","ORLIN":"0","UNIDADE":"UN","FACTOR":"1.0000","LINANU":"0","TPOPER":"2","DESCVO":".0000","VALORO":"84.0000","FORMUL":"0","CODLOT":"","ORDENACA":"1","LINHAREL":"0","DESCRRTF":"","ORDGER":"0","IMPRIME":"0","IDLINDOC":"48331","OPERNEW":"MICKAEL","DATENEW":"2022-10-26 00:00:00.000","HOURNEW":"08:54:11","PROCNEW":"1","OPERUPD":"MICKAEL","DATEUPD":"2022-10-26 00:00:00.000","HOURUPD":"08:54:11","PROCUPD":"1","SIGNATUR":"C4B00303D4A5F763946169E70133335E","INCOER":"0","ARTIGEAN":"","QTDRES":".0000","QTDRESOR":".0000","RESERVA_OBRA":"","VALOR_SAIDA_STOCK":".0000","VALOR_RETENCAO":".0000","TAXA_RETENCAO":".0000","CATEGORIA_RETENCAO":"0","MOVIMENTA_SO_VALOR":"0","VENDEDOR":"Gen","N_PRECO_LINHA_INTRODUZIDO":"1.4","N_VALOR_LINHA_INTRODUZIDO":"84.0000","N_TIPO_IVA":"4","N_IVA_LINHA":"19.3200","N_VALOR_TOTAL_DESCONTO":".0000","SERIE_ORIGINAL":"","NUMERO_ORIGINAL":"0","IMPOSTO_ALCOOL":".0000","ECOREEE":".0000","ECOEMBAL":".0000","ECOPILHA":".0000","ECOPNEU":".0000","ECOOUTRO":".0000","VLINTROR":"84.0000","VLIVAOR":"19.3200","VLTOTDESCOR":".0000","LINHAARRED":"0","MOTIVOISENCAOSAFT":"","QUANTIDADE_RETIFICADA":".0000","LINHA_RETIFICADA":"0","NUMERO_AUTORIZACAO":"","VERSAOCATALOGOS":"","CCUSTO":"","PROCESSO_ITEM":"","PROJETO":""},{"TPDOCUM":"FTP","NNUMDOC":"413","NUMLINHA":"1","TPLINHA":"1","ARTIGO":"4388","DESCR":"79327524    LAM.CORTE EXTENSAO","PRUNIT":"33.21","ENCARGOS":"0","QUANT":"3","VALOR":"99.6300","TXDESC":".0000","DESCONTO":"0","IVA":"23.0000","SERIE":"22","VLMOVORI":".0000","QTDORIG":"3.0000","ANO":"2022","RUBRICA":"","VLMOVSTK":".0000","DESCVAL":".0000","MOVSTC":"2","SECTOR":"ANS","ARMAZEM":"001","DATA":"2022-10-26 00:00:00.000","ORANO":"0","ORDOC":"","ORSERIE":"","ORNUM":"0","ORLIN":"0","UNIDADE":"UN","FACTOR":"1.0000","LINANU":"0","TPOPER":"2","DESCVO":".0000","VALORO":"99.6300","FORMUL":"0","CODLOT":"","ORDENACA":"1","LINHAREL":"0","DESCRRTF":"","ORDGER":"0","IMPRIME":"0","IDLINDOC":"48358","OPERNEW":"MICKAEL","DATENEW":"2022-10-26 00:00:00.000","HOURNEW":"13:31:02","PROCNEW":"1","OPERUPD":"MICKAEL","DATEUPD":"2022-10-26 00:00:00.000","HOURUPD":"13:31:02","PROCUPD":"1","SIGNATUR":"8C9C6C277BC95BBE0B7C6B9C91B86368","INCOER":"0","ARTIGEAN":"","QTDRES":".0000","QTDRESOR":".0000","RESERVA_OBRA":"","VALOR_SAIDA_STOCK":".0000","VALOR_RETENCAO":".0000","TAXA_RETENCAO":".0000","CATEGORIA_RETENCAO":"0","MOVIMENTA_SO_VALOR":"0","VENDEDOR":"Gen","N_PRECO_LINHA_INTRODUZIDO":"33.21","N_VALOR_LINHA_INTRODUZIDO":"99.6300","N_TIPO_IVA":"4","N_IVA_LINHA":"22.9149","N_VALOR_TOTAL_DESCONTO":".0000","SERIE_ORIGINAL":"","NUMERO_ORIGINAL":"0","IMPOSTO_ALCOOL":".0000","ECOREEE":".0000","ECOEMBAL":".0000","ECOPILHA":".0000","ECOPNEU":".0000","ECOOUTRO":".0000","VLINTROR":"99.6300","VLIVAOR":"22.9149","VLTOTDESCOR":".0000","LINHAARRED":"0","MOTIVOISENCAOSAFT":"","QUANTIDADE_RETIFICADA":".0000","LINHA_RETIFICADA":"0","NUMERO_AUTORIZACAO":"","VERSAOCATALOGOS":"","CCUSTO":"","PROCESSO_ITEM":"","PROJETO":""},{"TPDOCUM":"GTC","NNUMDOC":"317","NUMLINHA":"1","TPLINHA":"1","ARTIGO":"374000","DESCR":"MAQUINA BROTHER EF4-B511","PRUNIT":"0","ENCARGOS":"0","QUANT":"1","VALOR":".0000","TXDESC":".0000","DESCONTO":"0","IVA":"23.0000","SERIE":"2","VLMOVORI":".0000","QTDORIG":"1.0000","ANO":"2022","RUBRICA":"374000","VLMOVSTK":".0000","DESCVAL":".0000","MOVSTC":"0","SECTOR":"ANS","ARMAZEM":"","DATA":"2022-10-26 00:00:00.000","ORANO":"0","ORDOC":"","ORSERIE":"","ORNUM":"0","ORLIN":"0","UNIDADE":"","FACTOR":"1.0000","LINANU":"0","TPOPER":"2","DESCVO":".0000","VALORO":".0000","FORMUL":"0","CODLOT":"","ORDENACA":"1","LINHAREL":"0","DESCRRTF":"","ORDGER":"0","IMPRIME":"0","IDLINDOC":"48362","OPERNEW":"MICKAEL","DATENEW":"2022-10-26 00:00:00.000","HOURNEW":"15:00:05","PROCNEW":"1","OPERUPD":"MICKAEL","DATEUPD":"2022-10-26 00:00:00.000","HOURUPD":"15:00:05","PROCUPD":"1","SIGNATUR":"D7B204240F5A5FC076A1274E08F8E18E","INCOER":"0","ARTIGEAN":"","QTDRES":".0000","QTDRESOR":".0000","RESERVA_OBRA":"","VALOR_SAIDA_STOCK":".0000","VALOR_RETENCAO":".0000","TAXA_RETENCAO":".0000","CATEGORIA_RETENCAO":"0","MOVIMENTA_SO_VALOR":"0","VENDEDOR":"RES","N_PRECO_LINHA_INTRODUZIDO":"0","N_VALOR_LINHA_INTRODUZIDO":".0000","N_TIPO_IVA":"4","N_IVA_LINHA":".0000","N_VALOR_TOTAL_DESCONTO":".0000","SERIE_ORIGINAL":"","NUMERO_ORIGINAL":"0","IMPOSTO_ALCOOL":".0000","ECOREEE":".0000","ECOEMBAL":".0000","ECOPILHA":".0000","ECOPNEU":".0000","ECOOUTRO":".0000","VLINTROR":".0000","VLIVAOR":".0000","VLTOTDESCOR":".0000","LINHAARRED":"0","MOTIVOISENCAOSAFT":"","QUANTIDADE_RETIFICADA":".0000","LINHA_RETIFICADA":"0","NUMERO_AUTORIZACAO":"","VERSAOCATALOGOS":"","CCUSTO":"","PROCESSO_ITEM":"","PROJETO":""},{"TPDOCUM":"GTC","NNUMDOC":"317","NUMLINHA":"2","TPLINHA":"1","ARTIGO":"","DESCR":"N\u00ba SERIE: L1538924","PRUNIT":"0","ENCARGOS":"0","QUANT":"0","VALOR":".0000","TXDESC":".0000","DESCONTO":"0","IVA":".0000","SERIE":"2","VLMOVORI":".0000","QTDORIG":".0000","ANO":"2022","RUBRICA":"","VLMOVSTK":".0000","DESCVAL":".0000","MOVSTC":"0","SECTOR":"ANS","ARMAZEM":"","DATA":"2022-10-26 00:00:00.000","ORANO":"0","ORDOC":"","ORSERIE":"","ORNUM":"0","ORLIN":"0","UNIDADE":"","FACTOR":"1.0000","LINANU":"0","TPOPER":"0","DESCVO":".0000","VALORO":".0000","FORMUL":"0","CODLOT":"","ORDENACA":"2","LINHAREL":"0","DESCRRTF":"","ORDGER":"0","IMPRIME":"0","IDLINDOC":"48363","OPERNEW":"MICKAEL","DATENEW":"2022-10-26 00:00:00.000","HOURNEW":"15:00:05","PROCNEW":"1","OPERUPD":"MICKAEL","DATEUPD":"2022-10-26 00:00:00.000","HOURUPD":"15:00:05","PROCUPD":"1","SIGNATUR":"9D2B892E4485A77238AF335DBF721D90","INCOER":"0","ARTIGEAN":"","QTDRES":".0000","QTDRESOR":".0000","RESERVA_OBRA":"","VALOR_SAIDA_STOCK":".0000","VALOR_RETENCAO":".0000","TAXA_RETENCAO":".0000","CATEGORIA_RETENCAO":"0","MOVIMENTA_SO_VALOR":"0","VENDEDOR":"RES","N_PRECO_LINHA_INTRODUZIDO":"0","N_VALOR_LINHA_INTRODUZIDO":".0000","N_TIPO_IVA":"1","N_IVA_LINHA":".0000","N_VALOR_TOTAL_DESCONTO":".0000","SERIE_ORIGINAL":"","NUMERO_ORIGINAL":"0","IMPOSTO_ALCOOL":".0000","ECOREEE":".0000","ECOEMBAL":".0000","ECOPILHA":".0000","ECOPNEU":".0000","ECOOUTRO":".0000","VLINTROR":".0000","VLIVAOR":".0000","VLTOTDESCOR":".0000","LINHAARRED":"0","MOTIVOISENCAOSAFT":"","QUANTIDADE_RETIFICADA":".0000","LINHA_RETIFICADA":"0","NUMERO_AUTORIZACAO":"","VERSAOCATALOGOS":"","CCUSTO":"","PROCESSO_ITEM":"","PROJETO":""},{"TPDOCUM":"GTC","NNUMDOC":"317","NUMLINHA":"3","TPLINHA":"1","ARTIGO":"374000","DESCR":"MAQUINA SINGER 832U","PRUNIT":"0","ENCARGOS":"0","QUANT":"2","VALOR":".0000","TXDESC":".0000","DESCONTO":"0","IVA":"23.0000","SERIE":"2","VLMOVORI":".0000","QTDORIG":"2.0000","ANO":"2022","RUBRICA":"374000","VLMOVSTK":".0000","DESCVAL":".0000","MOVSTC":"0","SECTOR":"ANS","ARMAZEM":"","DATA":"2022-10-26 00:00:00.000","ORANO":"0","ORDOC":"","ORSERIE":"","ORNUM":"0","ORLIN":"0","UNIDADE":"","FACTOR":"1.0000","LINANU":"0","TPOPER":"2","DESCVO":".0000","VALORO":".0000","FORMUL":"0","CODLOT":"","ORDENACA":"3","LINHAREL":"0","DESCRRTF":"","ORDGER":"0","IMPRIME":"0","IDLINDOC":"48364","OPERNEW":"MICKAEL","DATENEW":"2022-10-26 00:00:00.000","HOURNEW":"15:00:05","PROCNEW":"1","OPERUPD":"MICKAEL","DATEUPD":"2022-10-26 00:00:00.000","HOURUPD":"15:00:05","PROCUPD":"1","SIGNATUR":"8C052580927A942B03D4EC393AF4451B","INCOER":"0","ARTIGEAN":"","QTDRES":".0000","QTDRESOR":".0000","RESERVA_OBRA":"","VALOR_SAIDA_STOCK":".0000","VALOR_RETENCAO":".0000","TAXA_RETENCAO":".0000","CATEGORIA_RETENCAO":"0","MOVIMENTA_SO_VALOR":"0","VENDEDOR":"RES","N_PRECO_LINHA_INTRODUZIDO":"0","N_VALOR_LINHA_INTRODUZIDO":".0000","N_TIPO_IVA":"4","N_IVA_LINHA":".0000","N_VALOR_TOTAL_DESCONTO":".0000","SERIE_ORIGINAL":"","NUMERO_ORIGINAL":"0","IMPOSTO_ALCOOL":".0000","ECOREEE":".0000","ECOEMBAL":".0000","ECOPILHA":".0000","ECOPNEU":".0000","ECOOUTRO":".0000","VLINTROR":".0000","VLIVAOR":".0000","VLTOTDESCOR":".0000","LINHAARRED":"0","MOTIVOISENCAOSAFT":"","QUANTIDADE_RETIFICADA":".0000","LINHA_RETIFICADA":"0","NUMERO_AUTORIZACAO":"","VERSAOCATALOGOS":"","CCUSTO":"","PROCESSO_ITEM":"","PROJETO":""},{"TPDOCUM":"GTC","NNUMDOC":"317","NUMLINHA":"4","TPLINHA":"1","ARTIGO":"","DESCR":"N\u00ba SERIE: B1566985 \/ H7545560","PRUNIT":"0","ENCARGOS":"0","QUANT":"0","VALOR":".0000","TXDESC":".0000","DESCONTO":"0","IVA":".0000","SERIE":"2","VLMOVORI":".0000","QTDORIG":".0000","ANO":"2022","RUBRICA":"","VLMOVSTK":".0000","DESCVAL":".0000","MOVSTC":"0","SECTOR":"ANS","ARMAZEM":"","DATA":"2022-10-26 00:00:00.000","ORANO":"0","ORDOC":"","ORSERIE":"","ORNUM":"0","ORLIN":"0","UNIDADE":"","FACTOR":"1.0000","LINANU":"0","TPOPER":"0","DESCVO":".0000","VALORO":".0000","FORMUL":"0","CODLOT":"","ORDENACA":"4","LINHAREL":"0","DESCRRTF":"","ORDGER":"0","IMPRIME":"0","IDLINDOC":"48365","OPERNEW":"MICKAEL","DATENEW":"2022-10-26 00:00:00.000","HOURNEW":"15:00:05","PROCNEW":"1","OPERUPD":"MICKAEL","DATEUPD":"2022-10-26 00:00:00.000","HOURUPD":"15:00:05","PROCUPD":"1","SIGNATUR":"AD43908514B96319DB30C4BB65CE1830","INCOER":"0","ARTIGEAN":"","QTDRES":".0000","QTDRESOR":".0000","RESERVA_OBRA":"","VALOR_SAIDA_STOCK":".0000","VALOR_RETENCAO":".0000","TAXA_RETENCAO":".0000","CATEGORIA_RETENCAO":"0","MOVIMENTA_SO_VALOR":"0","VENDEDOR":"RES","N_PRECO_LINHA_INTRODUZIDO":"0","N_VALOR_LINHA_INTRODUZIDO":".0000","N_TIPO_IVA":"1","N_IVA_LINHA":".0000","N_VALOR_TOTAL_DESCONTO":".0000","SERIE_ORIGINAL":"","NUMERO_ORIGINAL":"0","IMPOSTO_ALCOOL":".0000","ECOREEE":".0000","ECOEMBAL":".0000","ECOPILHA":".0000","ECOPNEU":".0000","ECOOUTRO":".0000","VLINTROR":".0000","VLIVAOR":".0000","VLTOTDESCOR":".0000","LINHAARRED":"0","MOTIVOISENCAOSAFT":"","QUANTIDADE_RETIFICADA":".0000","LINHA_RETIFICADA":"0","NUMERO_AUTORIZACAO":"","VERSAOCATALOGOS":"","CCUSTO":"","PROCESSO_ITEM":"","PROJETO":""},{"TPDOCUM":"GTC","NNUMDOC":"317","NUMLINHA":"5","TPLINHA":"1","ARTIGO":"374000","DESCR":"MAQUINA JUKI MO-2304","PRUNIT":"0","ENCARGOS":"0","QUANT":"1","VALOR":".0000","TXDESC":".0000","DESCONTO":"0","IVA":"23.0000","SERIE":"2","VLMOVORI":".0000","QTDORIG":"1.0000","ANO":"2022","RUBRICA":"374000","VLMOVSTK":".0000","DESCVAL":".0000","MOVSTC":"0","SECTOR":"ANS","ARMAZEM":"","DATA":"2022-10-26 00:00:00.000","ORANO":"0","ORDOC":"","ORSERIE":"","ORNUM":"0","ORLIN":"0","UNIDADE":"","FACTOR":"1.0000","LINANU":"0","TPOPER":"2","DESCVO":".0000","VALORO":".0000","FORMUL":"0","CODLOT":"","ORDENACA":"5","LINHAREL":"0","DESCRRTF":"","ORDGER":"0","IMPRIME":"0","IDLINDOC":"48366","OPERNEW":"MICKAEL","DATENEW":"2022-10-26 00:00:00.000","HOURNEW":"15:00:05","PROCNEW":"1","OPERUPD":"MICKAEL","DATEUPD":"2022-10-26 00:00:00.000","HOURUPD":"15:00:05","PROCUPD":"1","SIGNATUR":"C2E8F9B713383C3F40CE819F165D0800","INCOER":"0","ARTIGEAN":"","QTDRES":".0000","QTDRESOR":".0000","RESERVA_OBRA":"","VALOR_SAIDA_STOCK":".0000","VALOR_RETENCAO":".0000","TAXA_RETENCAO":".0000","CATEGORIA_RETENCAO":"0","MOVIMENTA_SO_VALOR":"0","VENDEDOR":"RES","N_PRECO_LINHA_INTRODUZIDO":"0","N_VALOR_LINHA_INTRODUZIDO":".0000","N_TIPO_IVA":"4","N_IVA_LINHA":".0000","N_VALOR_TOTAL_DESCONTO":".0000","SERIE_ORIGINAL":"","NUMERO_ORIGINAL":"0","IMPOSTO_ALCOOL":".0000","ECOREEE":".0000","ECOEMBAL":".0000","ECOPILHA":".0000","ECOPNEU":".0000","ECOOUTRO":".0000","VLINTROR":".0000","VLIVAOR":".0000","VLTOTDESCOR":".0000","LINHAARRED":"0","MOTIVOISENCAOSAFT":"","QUANTIDADE_RETIFICADA":".0000","LINHA_RETIFICADA":"0","NUMERO_AUTORIZACAO":"","VERSAOCATALOGOS":"","CCUSTO":"","PROCESSO_ITEM":"","PROJETO":""},{"TPDOCUM":"GTC","NNUMDOC":"317","NUMLINHA":"6","TPLINHA":"1","ARTIGO":"","DESCR":"N\u00ba SERIE: 2000-N71443","PRUNIT":"0","ENCARGOS":"0","QUANT":"0","VALOR":".0000","TXDESC":".0000","DESCONTO":"0","IVA":".0000","SERIE":"2","VLMOVORI":".0000","QTDORIG":".0000","ANO":"2022","RUBRICA":"","VLMOVSTK":".0000","DESCVAL":".0000","MOVSTC":"0","SECTOR":"ANS","ARMAZEM":"","DATA":"2022-10-26 00:00:00.000","ORANO":"0","ORDOC":"","ORSERIE":"","ORNUM":"0","ORLIN":"0","UNIDADE":"","FACTOR":"1.0000","LINANU":"0","TPOPER":"0","DESCVO":".0000","VALORO":".0000","FORMUL":"0","CODLOT":"","ORDENACA":"6","LINHAREL":"0","DESCRRTF":"","ORDGER":"0","IMPRIME":"0","IDLINDOC":"48367","OPERNEW":"MICKAEL","DATENEW":"2022-10-26 00:00:00.000","HOURNEW":"15:00:05","PROCNEW":"1","OPERUPD":"MICKAEL","DATEUPD":"2022-10-26 00:00:00.000","HOURUPD":"15:00:05","PROCUPD":"1","SIGNATUR":"A4C9A72FD50092A17E94B02F07482894","INCOER":"0","ARTIGEAN":"","QTDRES":".0000","QTDRESOR":".0000","RESERVA_OBRA":"","VALOR_SAIDA_STOCK":".0000","VALOR_RETENCAO":".0000","TAXA_RETENCAO":".0000","CATEGORIA_RETENCAO":"0","MOVIMENTA_SO_VALOR":"0","VENDEDOR":"RES","N_PRECO_LINHA_INTRODUZIDO":"0","N_VALOR_LINHA_INTRODUZIDO":".0000","N_TIPO_IVA":"1","N_IVA_LINHA":".0000","N_VALOR_TOTAL_DESCONTO":".0000","SERIE_ORIGINAL":"","NUMERO_ORIGINAL":"0","IMPOSTO_ALCOOL":".0000","ECOREEE":".0000","ECOEMBAL":".0000","ECOPILHA":".0000","ECOPNEU":".0000","ECOOUTRO":".0000","VLINTROR":".0000","VLIVAOR":".0000","VLTOTDESCOR":".0000","LINHAARRED":"0","MOTIVOISENCAOSAFT":"","QUANTIDADE_RETIFICADA":".0000","LINHA_RETIFICADA":"0","NUMERO_AUTORIZACAO":"","VERSAOCATALOGOS":"","CCUSTO":"","PROCESSO_ITEM":"","PROJETO":""},{"TPDOCUM":"GTC","NNUMDOC":"317","NUMLINHA":"7","TPLINHA":"1","ARTIGO":"374000","DESCR":"MAQUINA BROTHER EF4-B531","PRUNIT":"0","ENCARGOS":"0","QUANT":"1","VALOR":".0000","TXDESC":".0000","DESCONTO":"0","IVA":"23.0000","SERIE":"2","VLMOVORI":".0000","QTDORIG":"1.0000","ANO":"2022","RUBRICA":"374000","VLMOVSTK":".0000","DESCVAL":".0000","MOVSTC":"0","SECTOR":"ANS","ARMAZEM":"","DATA":"2022-10-26 00:00:00.000","ORANO":"0","ORDOC":"","ORSERIE":"","ORNUM":"0","ORLIN":"0","UNIDADE":"","FACTOR":"1.0000","LINANU":"0","TPOPER":"2","DESCVO":".0000","VALORO":".0000","FORMUL":"0","CODLOT":"","ORDENACA":"7","LINHAREL":"0","DESCRRTF":"","ORDGER":"0","IMPRIME":"0","IDLINDOC":"48368","OPERNEW":"MICKAEL","DATENEW":"2022-10-26 00:00:00.000","HOURNEW":"15:00:05","PROCNEW":"1","OPERUPD":"MICKAEL","DATEUPD":"2022-10-26 00:00:00.000","HOURUPD":"15:00:05","PROCUPD":"1","SIGNATUR":"81F33610708B7DE75B44D263D6312CBC","INCOER":"0","ARTIGEAN":"","QTDRES":".0000","QTDRESOR":".0000","RESERVA_OBRA":"","VALOR_SAIDA_STOCK":".0000","VALOR_RETENCAO":".0000","TAXA_RETENCAO":".0000","CATEGORIA_RETENCAO":"0","MOVIMENTA_SO_VALOR":"0","VENDEDOR":"RES","N_PRECO_LINHA_INTRODUZIDO":"0","N_VALOR_LINHA_INTRODUZIDO":".0000","N_TIPO_IVA":"4","N_IVA_LINHA":".0000","N_VALOR_TOTAL_DESCONTO":".0000","SERIE_ORIGINAL":"","NUMERO_ORIGINAL":"0","IMPOSTO_ALCOOL":".0000","ECOREEE":".0000","ECOEMBAL":".0000","ECOPILHA":".0000","ECOPNEU":".0000","ECOOUTRO":".0000","VLINTROR":".0000","VLIVAOR":".0000","VLTOTDESCOR":".0000","LINHAARRED":"0","MOTIVOISENCAOSAFT":"","QUANTIDADE_RETIFICADA":".0000","LINHA_RETIFICADA":"0","NUMERO_AUTORIZACAO":"","VERSAOCATALOGOS":"","CCUSTO":"","PROCESSO_ITEM":"","PROJETO":""},{"TPDOCUM":"GTC","NNUMDOC":"317","NUMLINHA":"8","TPLINHA":"1","ARTIGO":"","DESCR":"N\u00ba SERIE: B9547128","PRUNIT":"0","ENCARGOS":"0","QUANT":"0","VALOR":".0000","TXDESC":".0000","DESCONTO":"0","IVA":".0000","SERIE":"2","VLMOVORI":".0000","QTDORIG":".0000","ANO":"2022","RUBRICA":"","VLMOVSTK":".0000","DESCVAL":".0000","MOVSTC":"0","SECTOR":"ANS","ARMAZEM":"","DATA":"2022-10-26 00:00:00.000","ORANO":"0","ORDOC":"","ORSERIE":"","ORNUM":"0","ORLIN":"0","UNIDADE":"","FACTOR":"1.0000","LINANU":"0","TPOPER":"0","DESCVO":".0000","VALORO":".0000","FORMUL":"0","CODLOT":"","ORDENACA":"8","LINHAREL":"0","DESCRRTF":"","ORDGER":"0","IMPRIME":"0","IDLINDOC":"48369","OPERNEW":"MICKAEL","DATENEW":"2022-10-26 00:00:00.000","HOURNEW":"15:00:05","PROCNEW":"1","OPERUPD":"MICKAEL","DATEUPD":"2022-10-26 00:00:00.000","HOURUPD":"15:00:05","PROCUPD":"1","SIGNATUR":"09F1213A885613ED6A72ED0D7D6EA6EC","INCOER":"0","ARTIGEAN":"","QTDRES":".0000","QTDRESOR":".0000","RESERVA_OBRA":"","VALOR_SAIDA_STOCK":".0000","VALOR_RETENCAO":".0000","TAXA_RETENCAO":".0000","CATEGORIA_RETENCAO":"0","MOVIMENTA_SO_VALOR":"0","VENDEDOR":"RES","N_PRECO_LINHA_INTRODUZIDO":"0","N_VALOR_LINHA_INTRODUZIDO":".0000","N_TIPO_IVA":"1","N_IVA_LINHA":".0000","N_VALOR_TOTAL_DESCONTO":".0000","SERIE_ORIGINAL":"","NUMERO_ORIGINAL":"0","IMPOSTO_ALCOOL":".0000","ECOREEE":".0000","ECOEMBAL":".0000","ECOPILHA":".0000","ECOPNEU":".0000","ECOOUTRO":".0000","VLINTROR":".0000","VLIVAOR":".0000","VLTOTDESCOR":".0000","LINHAARRED":"0","MOTIVOISENCAOSAFT":"","QUANTIDADE_RETIFICADA":".0000","LINHA_RETIFICADA":"0","NUMERO_AUTORIZACAO":"","VERSAOCATALOGOS":"","CCUSTO":"","PROCESSO_ITEM":"","PROJETO":""},{"TPDOCUM":"GTC","NNUMDOC":"317","NUMLINHA":"9","TPLINHA":"1","ARTIGO":"","DESCR":"(ENTREGA)","PRUNIT":"0","ENCARGOS":"0","QUANT":"0","VALOR":".0000","TXDESC":".0000","DESCONTO":"0","IVA":".0000","SERIE":"2","VLMOVORI":".0000","QTDORIG":".0000","ANO":"2022","RUBRICA":"","VLMOVSTK":".0000","DESCVAL":".0000","MOVSTC":"0","SECTOR":"ANS","ARMAZEM":"","DATA":"2022-10-26 00:00:00.000","ORANO":"0","ORDOC":"","ORSERIE":"","ORNUM":"0","ORLIN":"0","UNIDADE":"","FACTOR":"1.0000","LINANU":"0","TPOPER":"0","DESCVO":".0000","VALORO":".0000","FORMUL":"0","CODLOT":"","ORDENACA":"9","LINHAREL":"0","DESCRRTF":"","ORDGER":"0","IMPRIME":"0","IDLINDOC":"48370","OPERNEW":"MICKAEL","DATENEW":"2022-10-26 00:00:00.000","HOURNEW":"15:00:05","PROCNEW":"1","OPERUPD":"MICKAEL","DATEUPD":"2022-10-26 00:00:00.000","HOURUPD":"15:00:05","PROCUPD":"1","SIGNATUR":"4F2FED3050AAD9975278B29E0F556C3B","INCOER":"0","ARTIGEAN":"","QTDRES":".0000","QTDRESOR":".0000","RESERVA_OBRA":"","VALOR_SAIDA_STOCK":".0000","VALOR_RETENCAO":".0000","TAXA_RETENCAO":".0000","CATEGORIA_RETENCAO":"0","MOVIMENTA_SO_VALOR":"0","VENDEDOR":"RES","N_PRECO_LINHA_INTRODUZIDO":"0","N_VALOR_LINHA_INTRODUZIDO":".0000","N_TIPO_IVA":"1","N_IVA_LINHA":".0000","N_VALOR_TOTAL_DESCONTO":".0000","SERIE_ORIGINAL":"","NUMERO_ORIGINAL":"0","IMPOSTO_ALCOOL":".0000","ECOREEE":".0000","ECOEMBAL":".0000","ECOPILHA":".0000","ECOPNEU":".0000","ECOOUTRO":".0000","VLINTROR":".0000","VLIVAOR":".0000","VLTOTDESCOR":".0000","LINHAARRED":"0","MOTIVOISENCAOSAFT":"","QUANTIDADE_RETIFICADA":".0000","LINHA_RETIFICADA":"0","NUMERO_AUTORIZACAO":"","VERSAOCATALOGOS":"","CCUSTO":"","PROCESSO_ITEM":"","PROJETO":""},{"TPDOCUM":"PF","NNUMDOC":"30","NUMLINHA":"1","TPLINHA":"1","ARTIGO":"374000","DESCR":"MAQUINA ULTRASOM AC SEW  30KHZ","PRUNIT":"12000","ENCARGOS":"0","QUANT":"4","VALOR":"48000.0000","TXDESC":".0000","DESCONTO":"0","IVA":"23.0000","SERIE":"22","VLMOVORI":".0000","QTDORIG":"4.0000","ANO":"2022","RUBRICA":"374000","VLMOVSTK":".0000","DESCVAL":".0000","MOVSTC":"0","SECTOR":"ANS","ARMAZEM":"","DATA":"2022-10-26 00:00:00.000","ORANO":"0","ORDOC":"","ORSERIE":"0","ORNUM":"0","ORLIN":"0","UNIDADE":"","FACTOR":"1.0000","LINANU":"0","TPOPER":"2","DESCVO":".0000","VALORO":"48000.0000","FORMUL":"0","CODLOT":"","ORDENACA":"1","LINHAREL":"0","DESCRRTF":"","ORDGER":"0","IMPRIME":"0","IDLINDOC":"48333","OPERNEW":"MICKAEL","DATENEW":"2022-10-26 00:00:00.000","HOURNEW":"09:31:51","PROCNEW":"1","OPERUPD":"MICKAEL","DATEUPD":"2022-10-26 00:00:00.000","HOURUPD":"09:31:51","PROCUPD":"1","SIGNATUR":"D1FAA546F88B496D2BD2F526664CFFF3","INCOER":"0","ARTIGEAN":"","QTDRES":".0000","QTDRESOR":".0000","RESERVA_OBRA":"","VALOR_SAIDA_STOCK":".0000","VALOR_RETENCAO":".0000","TAXA_RETENCAO":".0000","CATEGORIA_RETENCAO":"0","MOVIMENTA_SO_VALOR":"0","VENDEDOR":"Gen","N_PRECO_LINHA_INTRODUZIDO":"12000","N_VALOR_LINHA_INTRODUZIDO":"48000.0000","N_TIPO_IVA":"4","N_IVA_LINHA":"11040.0000","N_VALOR_TOTAL_DESCONTO":".0000","SERIE_ORIGINAL":"","NUMERO_ORIGINAL":"0","IMPOSTO_ALCOOL":".0000","ECOREEE":".0000","ECOEMBAL":".0000","ECOPILHA":".0000","ECOPNEU":".0000","ECOOUTRO":".0000","VLINTROR":"48000.0000","VLIVAOR":"11040.0000","VLTOTDESCOR":".0000","LINHAARRED":"0","MOTIVOISENCAOSAFT":"","QUANTIDADE_RETIFICADA":".0000","LINHA_RETIFICADA":"0","NUMERO_AUTORIZACAO":"","VERSAOCATALOGOS":"","CCUSTO":"","PROCESSO_ITEM":"","PROJETO":""},{"TPDOCUM":"PF","NNUMDOC":"30","NUMLINHA":"2","TPLINHA":"1","ARTIGO":"","DESCR":"EQUIPADA C\/ SONOTRODO CIRCULAR","PRUNIT":"0","ENCARGOS":"0","QUANT":"0","VALOR":".0000","TXDESC":".0000","DESCONTO":"0","IVA":".0000","SERIE":"22","VLMOVORI":".0000","QTDORIG":".0000","ANO":"2022","RUBRICA":"","VLMOVSTK":".0000","DESCVAL":".0000","MOVSTC":"0","SECTOR":"ANS","ARMAZEM":"","DATA":"2022-10-26 00:00:00.000","ORANO":"0","ORDOC":"","ORSERIE":"0","ORNUM":"0","ORLIN":"0","UNIDADE":"","FACTOR":"1.0000","LINANU":"0","TPOPER":"0","DESCVO":".0000","VALORO":".0000","FORMUL":"0","CODLOT":"","ORDENACA":"2","LINHAREL":"0","DESCRRTF":"","ORDGER":"0","IMPRIME":"0","IDLINDOC":"48334","OPERNEW":"MICKAEL","DATENEW":"2022-10-26 00:00:00.000","HOURNEW":"09:31:51","PROCNEW":"1","OPERUPD":"MICKAEL","DATEUPD":"2022-10-26 00:00:00.000","HOURUPD":"09:31:51","PROCUPD":"1","SIGNATUR":"EFCF85C4AC91929895FA66366F122431","INCOER":"0","ARTIGEAN":"","QTDRES":".0000","QTDRESOR":".0000","RESERVA_OBRA":"","VALOR_SAIDA_STOCK":".0000","VALOR_RETENCAO":".0000","TAXA_RETENCAO":".0000","CATEGORIA_RETENCAO":"0","MOVIMENTA_SO_VALOR":"0","VENDEDOR":"Gen","N_PRECO_LINHA_INTRODUZIDO":"0","N_VALOR_LINHA_INTRODUZIDO":".0000","N_TIPO_IVA":"1","N_IVA_LINHA":".0000","N_VALOR_TOTAL_DESCONTO":".0000","SERIE_ORIGINAL":"","NUMERO_ORIGINAL":"0","IMPOSTO_ALCOOL":".0000","ECOREEE":".0000","ECOEMBAL":".0000","ECOPILHA":".0000","ECOPNEU":".0000","ECOOUTRO":".0000","VLINTROR":".0000","VLIVAOR":".0000","VLTOTDESCOR":".0000","LINHAARRED":"0","MOTIVOISENCAOSAFT":"","QUANTIDADE_RETIFICADA":".0000","LINHA_RETIFICADA":"0","NUMERO_AUTORIZACAO":"","VERSAOCATALOGOS":"","CCUSTO":"","PROCESSO_ITEM":"","PROJETO":""},{"TPDOCUM":"PF","NNUMDOC":"30","NUMLINHA":"3","TPLINHA":"1","ARTIGO":"","DESCR":"","PRUNIT":"0","ENCARGOS":"0","QUANT":"0","VALOR":".0000","TXDESC":".0000","DESCONTO":"0","IVA":".0000","SERIE":"22","VLMOVORI":".0000","QTDORIG":".0000","ANO":"2022","RUBRICA":"","VLMOVSTK":".0000","DESCVAL":".0000","MOVSTC":"0","SECTOR":"ANS","ARMAZEM":"","DATA":"2022-10-26 00:00:00.000","ORANO":"0","ORDOC":"","ORSERIE":"0","ORNUM":"0","ORLIN":"0","UNIDADE":"","FACTOR":"1.0000","LINANU":"0","TPOPER":"0","DESCVO":".0000","VALORO":".0000","FORMUL":"0","CODLOT":"","ORDENACA":"3","LINHAREL":"0","DESCRRTF":"","ORDGER":"0","IMPRIME":"0","IDLINDOC":"48335","OPERNEW":"MICKAEL","DATENEW":"2022-10-26 00:00:00.000","HOURNEW":"09:31:51","PROCNEW":"1","OPERUPD":"MICKAEL","DATEUPD":"2022-10-26 00:00:00.000","HOURUPD":"09:31:51","PROCUPD":"1","SIGNATUR":"C25E331769885FDEE0860AD528B0F237","INCOER":"0","ARTIGEAN":"","QTDRES":".0000","QTDRESOR":".0000","RESERVA_OBRA":"","VALOR_SAIDA_STOCK":".0000","VALOR_RETENCAO":".0000","TAXA_RETENCAO":".0000","CATEGORIA_RETENCAO":"0","MOVIMENTA_SO_VALOR":"0","VENDEDOR":"Gen","N_PRECO_LINHA_INTRODUZIDO":"0","N_VALOR_LINHA_INTRODUZIDO":".0000","N_TIPO_IVA":"1","N_IVA_LINHA":".0000","N_VALOR_TOTAL_DESCONTO":".0000","SERIE_ORIGINAL":"","NUMERO_ORIGINAL":"0","IMPOSTO_ALCOOL":".0000","ECOREEE":".0000","ECOEMBAL":".0000","ECOPILHA":".0000","ECOPNEU":".0000","ECOOUTRO":".0000","VLINTROR":".0000","VLIVAOR":".0000","VLTOTDESCOR":".0000","LINHAARRED":"0","MOTIVOISENCAOSAFT":"","QUANTIDADE_RETIFICADA":".0000","LINHA_RETIFICADA":"0","NUMERO_AUTORIZACAO":"","VERSAOCATALOGOS":"","CCUSTO":"","PROCESSO_ITEM":"","PROJETO":""},{"TPDOCUM":"PF","NNUMDOC":"30","NUMLINHA":"4","TPLINHA":"1","ARTIGO":"374000","DESCR":"MAQUINA DE COLUNA ULTRA-SOM AC SEW","PRUNIT":"8000","ENCARGOS":"0","QUANT":"1","VALOR":"8000.0000","TXDESC":".0000","DESCONTO":"0","IVA":"23.0000","SERIE":"22","VLMOVORI":".0000","QTDORIG":"1.0000","ANO":"2022","RUBRICA":"374000","VLMOVSTK":".0000","DESCVAL":".0000","MOVSTC":"0","SECTOR":"ANS","ARMAZEM":"","DATA":"2022-10-26 00:00:00.000","ORANO":"0","ORDOC":"","ORSERIE":"0","ORNUM":"0","ORLIN":"0","UNIDADE":"","FACTOR":"1.0000","LINANU":"0","TPOPER":"2","DESCVO":".0000","VALORO":"8000.0000","FORMUL":"0","CODLOT":"","ORDENACA":"4","LINHAREL":"0","DESCRRTF":"","ORDGER":"0","IMPRIME":"0","IDLINDOC":"48336","OPERNEW":"MICKAEL","DATENEW":"2022-10-26 00:00:00.000","HOURNEW":"09:31:51","PROCNEW":"1","OPERUPD":"MICKAEL","DATEUPD":"2022-10-26 00:00:00.000","HOURUPD":"09:31:51","PROCUPD":"1","SIGNATUR":"1CB9C1F998B2995A818CD94120577C98","INCOER":"0","ARTIGEAN":"","QTDRES":".0000","QTDRESOR":".0000","RESERVA_OBRA":"","VALOR_SAIDA_STOCK":".0000","VALOR_RETENCAO":".0000","TAXA_RETENCAO":".0000","CATEGORIA_RETENCAO":"0","MOVIMENTA_SO_VALOR":"0","VENDEDOR":"Gen","N_PRECO_LINHA_INTRODUZIDO":"8000","N_VALOR_LINHA_INTRODUZIDO":"8000.0000","N_TIPO_IVA":"4","N_IVA_LINHA":"1840.0000","N_VALOR_TOTAL_DESCONTO":".0000","SERIE_ORIGINAL":"","NUMERO_ORIGINAL":"0","IMPOSTO_ALCOOL":".0000","ECOREEE":".0000","ECOEMBAL":".0000","ECOPILHA":".0000","ECOPNEU":".0000","ECOOUTRO":".0000","VLINTROR":"8000.0000","VLIVAOR":"1840.0000","VLTOTDESCOR":".0000","LINHAARRED":"0","MOTIVOISENCAOSAFT":"","QUANTIDADE_RETIFICADA":".0000","LINHA_RETIFICADA":"0","NUMERO_AUTORIZACAO":"","VERSAOCATALOGOS":"","CCUSTO":"","PROCESSO_ITEM":"","PROJETO":""},{"TPDOCUM":"PF","NNUMDOC":"31","NUMLINHA":"1","TPLINHA":"1","ARTIGO":"374000","DESCR":"MAQUINA ULTRASOM 30KHZ","PRUNIT":"12000","ENCARGOS":"0","QUANT":"4","VALOR":"48000.0000","TXDESC":".0000","DESCONTO":"0","IVA":"23.0000","SERIE":"22","VLMOVORI":".0000","QTDORIG":"4.0000","ANO":"2022","RUBRICA":"374000","VLMOVSTK":".0000","DESCVAL":".0000","MOVSTC":"0","SECTOR":"ANS","ARMAZEM":"","DATA":"2022-10-26 00:00:00.000","ORANO":"0","ORDOC":"","ORSERIE":"0","ORNUM":"0","ORLIN":"0","UNIDADE":"","FACTOR":"1.0000","LINANU":"0","TPOPER":"2","DESCVO":".0000","VALORO":"48000.0000","FORMUL":"0","CODLOT":"","ORDENACA":"1","LINHAREL":"0","DESCRRTF":"","ORDGER":"0","IMPRIME":"0","IDLINDOC":"48345","OPERNEW":"MICKAEL","DATENEW":"2022-10-26 00:00:00.000","HOURNEW":"11:29:08","PROCNEW":"1","OPERUPD":"MICKAEL","DATEUPD":"2022-10-26 00:00:00.000","HOURUPD":"11:29:08","PROCUPD":"1","SIGNATUR":"A9F914F1334A0A1C1D46935F35922C7B","INCOER":"0","ARTIGEAN":"","QTDRES":".0000","QTDRESOR":".0000","RESERVA_OBRA":"","VALOR_SAIDA_STOCK":".0000","VALOR_RETENCAO":".0000","TAXA_RETENCAO":".0000","CATEGORIA_RETENCAO":"0","MOVIMENTA_SO_VALOR":"0","VENDEDOR":"Gen","N_PRECO_LINHA_INTRODUZIDO":"12000","N_VALOR_LINHA_INTRODUZIDO":"48000.0000","N_TIPO_IVA":"4","N_IVA_LINHA":"11040.0000","N_VALOR_TOTAL_DESCONTO":".0000","SERIE_ORIGINAL":"","NUMERO_ORIGINAL":"0","IMPOSTO_ALCOOL":".0000","ECOREEE":".0000","ECOEMBAL":".0000","ECOPILHA":".0000","ECOPNEU":".0000","ECOOUTRO":".0000","VLINTROR":"48000.0000","VLIVAOR":"11040.0000","VLTOTDESCOR":".0000","LINHAARRED":"0","MOTIVOISENCAOSAFT":"","QUANTIDADE_RETIFICADA":".0000","LINHA_RETIFICADA":"0","NUMERO_AUTORIZACAO":"","VERSAOCATALOGOS":"","CCUSTO":"","PROCESSO_ITEM":"","PROJETO":""},{"TPDOCUM":"PF","NNUMDOC":"31","NUMLINHA":"2","TPLINHA":"1","ARTIGO":"","DESCR":"EQUIPADA C\/ SONOTRODO CIRCULAR","PRUNIT":"0","ENCARGOS":"0","QUANT":"0","VALOR":".0000","TXDESC":".0000","DESCONTO":"0","IVA":".0000","SERIE":"22","VLMOVORI":".0000","QTDORIG":".0000","ANO":"2022","RUBRICA":"","VLMOVSTK":".0000","DESCVAL":".0000","MOVSTC":"0","SECTOR":"ANS","ARMAZEM":"","DATA":"2022-10-26 00:00:00.000","ORANO":"0","ORDOC":"","ORSERIE":"0","ORNUM":"0","ORLIN":"0","UNIDADE":"","FACTOR":"1.0000","LINANU":"0","TPOPER":"0","DESCVO":".0000","VALORO":".0000","FORMUL":"0","CODLOT":"","ORDENACA":"4","LINHAREL":"0","DESCRRTF":"","ORDGER":"0","IMPRIME":"0","IDLINDOC":"48346","OPERNEW":"MICKAEL","DATENEW":"2022-10-26 00:00:00.000","HOURNEW":"11:29:08","PROCNEW":"1","OPERUPD":"MICKAEL","DATEUPD":"2022-10-26 00:00:00.000","HOURUPD":"11:29:08","PROCUPD":"1","SIGNATUR":"F73B2954FB626761E83581B4A4036958","INCOER":"0","ARTIGEAN":"","QTDRES":".0000","QTDRESOR":".0000","RESERVA_OBRA":"","VALOR_SAIDA_STOCK":".0000","VALOR_RETENCAO":".0000","TAXA_RETENCAO":".0000","CATEGORIA_RETENCAO":"0","MOVIMENTA_SO_VALOR":"0","VENDEDOR":"Gen","N_PRECO_LINHA_INTRODUZIDO":"0","N_VALOR_LINHA_INTRODUZIDO":".0000","N_TIPO_IVA":"1","N_IVA_LINHA":".0000","N_VALOR_TOTAL_DESCONTO":".0000","SERIE_ORIGINAL":"","NUMERO_ORIGINAL":"0","IMPOSTO_ALCOOL":".0000","ECOREEE":".0000","ECOEMBAL":".0000","ECOPILHA":".0000","ECOPNEU":".0000","ECOOUTRO":".0000","VLINTROR":".0000","VLIVAOR":".0000","VLTOTDESCOR":".0000","LINHAARRED":"0","MOTIVOISENCAOSAFT":"","QUANTIDADE_RETIFICADA":".0000","LINHA_RETIFICADA":"0","NUMERO_AUTORIZACAO":"","VERSAOCATALOGOS":"","CCUSTO":"","PROCESSO_ITEM":"","PROJETO":""},{"TPDOCUM":"PF","NNUMDOC":"31","NUMLINHA":"3","TPLINHA":"1","ARTIGO":"","DESCR":"","PRUNIT":"0","ENCARGOS":"0","QUANT":"0","VALOR":".0000","TXDESC":".0000","DESCONTO":"0","IVA":".0000","SERIE":"22","VLMOVORI":".0000","QTDORIG":".0000","ANO":"2022","RUBRICA":"","VLMOVSTK":".0000","DESCVAL":".0000","MOVSTC":"0","SECTOR":"ANS","ARMAZEM":"","DATA":"2022-10-26 00:00:00.000","ORANO":"0","ORDOC":"","ORSERIE":"0","ORNUM":"0","ORLIN":"0","UNIDADE":"","FACTOR":"1.0000","LINANU":"0","TPOPER":"0","DESCVO":".0000","VALORO":".0000","FORMUL":"0","CODLOT":"","ORDENACA":"5","LINHAREL":"0","DESCRRTF":"","ORDGER":"0","IMPRIME":"0","IDLINDOC":"48347","OPERNEW":"MICKAEL","DATENEW":"2022-10-26 00:00:00.000","HOURNEW":"11:29:08","PROCNEW":"1","OPERUPD":"MICKAEL","DATEUPD":"2022-10-26 00:00:00.000","HOURUPD":"11:29:08","PROCUPD":"1","SIGNATUR":"E09B940C6314C1FCF47971D56B600213","INCOER":"0","ARTIGEAN":"","QTDRES":".0000","QTDRESOR":".0000","RESERVA_OBRA":"","VALOR_SAIDA_STOCK":".0000","VALOR_RETENCAO":".0000","TAXA_RETENCAO":".0000","CATEGORIA_RETENCAO":"0","MOVIMENTA_SO_VALOR":"0","VENDEDOR":"Gen","N_PRECO_LINHA_INTRODUZIDO":"0","N_VALOR_LINHA_INTRODUZIDO":".0000","N_TIPO_IVA":"1","N_IVA_LINHA":".0000","N_VALOR_TOTAL_DESCONTO":".0000","SERIE_ORIGINAL":"","NUMERO_ORIGINAL":"0","IMPOSTO_ALCOOL":".0000","ECOREEE":".0000","ECOEMBAL":".0000","ECOPILHA":".0000","ECOPNEU":".0000","ECOOUTRO":".0000","VLINTROR":".0000","VLIVAOR":".0000","VLTOTDESCOR":".0000","LINHAARRED":"0","MOTIVOISENCAOSAFT":"","QUANTIDADE_RETIFICADA":".0000","LINHA_RETIFICADA":"0","NUMERO_AUTORIZACAO":"","VERSAOCATALOGOS":"","CCUSTO":"","PROCESSO_ITEM":"","PROJETO":""},{"TPDOCUM":"PF","NNUMDOC":"31","NUMLINHA":"4","TPLINHA":"1","ARTIGO":"374000","DESCR":"MAQUINA DE COLUNA ULTRA-SOM ","PRUNIT":"8000","ENCARGOS":"0","QUANT":"1","VALOR":"8000.0000","TXDESC":".0000","DESCONTO":"0","IVA":"23.0000","SERIE":"22","VLMOVORI":".0000","QTDORIG":"1.0000","ANO":"2022","RUBRICA":"374000","VLMOVSTK":".0000","DESCVAL":".0000","MOVSTC":"0","SECTOR":"ANS","ARMAZEM":"","DATA":"2022-10-26 00:00:00.000","ORANO":"0","ORDOC":"","ORSERIE":"0","ORNUM":"0","ORLIN":"0","UNIDADE":"","FACTOR":"1.0000","LINANU":"0","TPOPER":"2","DESCVO":".0000","VALORO":"8000.0000","FORMUL":"0","CODLOT":"","ORDENACA":"6","LINHAREL":"0","DESCRRTF":"","ORDGER":"0","IMPRIME":"0","IDLINDOC":"48348","OPERNEW":"MICKAEL","DATENEW":"2022-10-26 00:00:00.000","HOURNEW":"11:29:08","PROCNEW":"1","OPERUPD":"MICKAEL","DATEUPD":"2022-10-26 00:00:00.000","HOURUPD":"11:29:08","PROCUPD":"1","SIGNATUR":"45884099F94566F69560DF3ADD7D090F","INCOER":"0","ARTIGEAN":"","QTDRES":".0000","QTDRESOR":".0000","RESERVA_OBRA":"","VALOR_SAIDA_STOCK":".0000","VALOR_RETENCAO":".0000","TAXA_RETENCAO":".0000","CATEGORIA_RETENCAO":"0","MOVIMENTA_SO_VALOR":"0","VENDEDOR":"Gen","N_PRECO_LINHA_INTRODUZIDO":"8000","N_VALOR_LINHA_INTRODUZIDO":"8000.0000","N_TIPO_IVA":"4","N_IVA_LINHA":"1840.0000","N_VALOR_TOTAL_DESCONTO":".0000","SERIE_ORIGINAL":"","NUMERO_ORIGINAL":"0","IMPOSTO_ALCOOL":".0000","ECOREEE":".0000","ECOEMBAL":".0000","ECOPILHA":".0000","ECOPNEU":".0000","ECOOUTRO":".0000","VLINTROR":"8000.0000","VLIVAOR":"1840.0000","VLTOTDESCOR":".0000","LINHAARRED":"0","MOTIVOISENCAOSAFT":"","QUANTIDADE_RETIFICADA":".0000","LINHA_RETIFICADA":"0","NUMERO_AUTORIZACAO":"","VERSAOCATALOGOS":"","CCUSTO":"","PROCESSO_ITEM":"","PROJETO":""},{"TPDOCUM":"PF","NNUMDOC":"31","NUMLINHA":"5","TPLINHA":"1","ARTIGO":"","DESCR":"MARCA: AC SEW","PRUNIT":"0","ENCARGOS":"0","QUANT":"0","VALOR":".0000","TXDESC":".0000","DESCONTO":"0","IVA":".0000","SERIE":"22","VLMOVORI":".0000","QTDORIG":".0000","ANO":"2022","RUBRICA":"","VLMOVSTK":".0000","DESCVAL":".0000","MOVSTC":"0","SECTOR":"","ARMAZEM":"","DATA":"2022-10-26 00:00:00.000","ORANO":"0","ORDOC":"","ORSERIE":"","ORNUM":"0","ORLIN":"0","UNIDADE":"","FACTOR":"1.0000","LINANU":"0","TPOPER":"0","DESCVO":".0000","VALORO":".0000","FORMUL":"0","CODLOT":"","ORDENACA":"2","LINHAREL":"0","DESCRRTF":"","ORDGER":"0","IMPRIME":"0","IDLINDOC":"48349","OPERNEW":"MICKAEL","DATENEW":"2022-10-26 00:00:00.000","HOURNEW":"11:29:08","PROCNEW":"1","OPERUPD":"MICKAEL","DATEUPD":"2022-10-26 00:00:00.000","HOURUPD":"11:29:08","PROCUPD":"1","SIGNATUR":"9D74E7D0732424541CEB9A59753E3733","INCOER":"0","ARTIGEAN":"","QTDRES":".0000","QTDRESOR":".0000","RESERVA_OBRA":"","VALOR_SAIDA_STOCK":".0000","VALOR_RETENCAO":".0000","TAXA_RETENCAO":".0000","CATEGORIA_RETENCAO":"0","MOVIMENTA_SO_VALOR":"0","VENDEDOR":"Gen","N_PRECO_LINHA_INTRODUZIDO":"0","N_VALOR_LINHA_INTRODUZIDO":".0000","N_TIPO_IVA":"1","N_IVA_LINHA":".0000","N_VALOR_TOTAL_DESCONTO":".0000","SERIE_ORIGINAL":"","NUMERO_ORIGINAL":"0","IMPOSTO_ALCOOL":".0000","ECOREEE":".0000","ECOEMBAL":".0000","ECOPILHA":".0000","ECOPNEU":".0000","ECOOUTRO":".0000","VLINTROR":".0000","VLIVAOR":".0000","VLTOTDESCOR":".0000","LINHAARRED":"0","MOTIVOISENCAOSAFT":"","QUANTIDADE_RETIFICADA":".0000","LINHA_RETIFICADA":"0","NUMERO_AUTORIZACAO":"","VERSAOCATALOGOS":"","CCUSTO":"","PROCESSO_ITEM":"","PROJETO":""},{"TPDOCUM":"PF","NNUMDOC":"31","NUMLINHA":"6","TPLINHA":"1","ARTIGO":"","DESCR":"MODELO: AC100","PRUNIT":"0","ENCARGOS":"0","QUANT":"0","VALOR":".0000","TXDESC":".0000","DESCONTO":"0","IVA":".0000","SERIE":"22","VLMOVORI":".0000","QTDORIG":".0000","ANO":"2022","RUBRICA":"","VLMOVSTK":".0000","DESCVAL":".0000","MOVSTC":"0","SECTOR":"","ARMAZEM":"","DATA":"2022-10-26 00:00:00.000","ORANO":"0","ORDOC":"","ORSERIE":"","ORNUM":"0","ORLIN":"0","UNIDADE":"","FACTOR":"1.0000","LINANU":"0","TPOPER":"0","DESCVO":".0000","VALORO":".0000","FORMUL":"0","CODLOT":"","ORDENACA":"3","LINHAREL":"0","DESCRRTF":"","ORDGER":"0","IMPRIME":"0","IDLINDOC":"48350","OPERNEW":"MICKAEL","DATENEW":"2022-10-26 00:00:00.000","HOURNEW":"11:29:08","PROCNEW":"1","OPERUPD":"MICKAEL","DATEUPD":"2022-10-26 00:00:00.000","HOURUPD":"11:29:08","PROCUPD":"1","SIGNATUR":"5791FAC678801340A56B1CEDD50C52B0","INCOER":"0","ARTIGEAN":"","QTDRES":".0000","QTDRESOR":".0000","RESERVA_OBRA":"","VALOR_SAIDA_STOCK":".0000","VALOR_RETENCAO":".0000","TAXA_RETENCAO":".0000","CATEGORIA_RETENCAO":"0","MOVIMENTA_SO_VALOR":"0","VENDEDOR":"Gen","N_PRECO_LINHA_INTRODUZIDO":"0","N_VALOR_LINHA_INTRODUZIDO":".0000","N_TIPO_IVA":"1","N_IVA_LINHA":".0000","N_VALOR_TOTAL_DESCONTO":".0000","SERIE_ORIGINAL":"","NUMERO_ORIGINAL":"0","IMPOSTO_ALCOOL":".0000","ECOREEE":".0000","ECOEMBAL":".0000","ECOPILHA":".0000","ECOPNEU":".0000","ECOOUTRO":".0000","VLINTROR":".0000","VLIVAOR":".0000","VLTOTDESCOR":".0000","LINHAARRED":"0","MOTIVOISENCAOSAFT":"","QUANTIDADE_RETIFICADA":".0000","LINHA_RETIFICADA":"0","NUMERO_AUTORIZACAO":"","VERSAOCATALOGOS":"","CCUSTO":"","PROCESSO_ITEM":"","PROJETO":""},{"TPDOCUM":"PF","NNUMDOC":"31","NUMLINHA":"7","TPLINHA":"1","ARTIGO":"","DESCR":"MARCA: AC SEW","PRUNIT":"0","ENCARGOS":"0","QUANT":"0","VALOR":".0000","TXDESC":".0000","DESCONTO":"0","IVA":".0000","SERIE":"22","VLMOVORI":".0000","QTDORIG":".0000","ANO":"2022","RUBRICA":"","VLMOVSTK":".0000","DESCVAL":".0000","MOVSTC":"0","SECTOR":"ANS","ARMAZEM":"","DATA":"2022-10-26 00:00:00.000","ORANO":"0","ORDOC":"","ORSERIE":"","ORNUM":"0","ORLIN":"0","UNIDADE":"","FACTOR":"1.0000","LINANU":"0","TPOPER":"0","DESCVO":".0000","VALORO":".0000","FORMUL":"0","CODLOT":"","ORDENACA":"7","LINHAREL":"0","DESCRRTF":"","ORDGER":"0","IMPRIME":"0","IDLINDOC":"48351","OPERNEW":"MICKAEL","DATENEW":"2022-10-26 00:00:00.000","HOURNEW":"11:29:08","PROCNEW":"1","OPERUPD":"MICKAEL","DATEUPD":"2022-10-26 00:00:00.000","HOURUPD":"11:29:08","PROCUPD":"1","SIGNATUR":"EF4870844030FE7845C13FBBABF76837","INCOER":"0","ARTIGEAN":"","QTDRES":".0000","QTDRESOR":".0000","RESERVA_OBRA":"","VALOR_SAIDA_STOCK":".0000","VALOR_RETENCAO":".0000","TAXA_RETENCAO":".0000","CATEGORIA_RETENCAO":"0","MOVIMENTA_SO_VALOR":"0","VENDEDOR":"Gen","N_PRECO_LINHA_INTRODUZIDO":"0","N_VALOR_LINHA_INTRODUZIDO":".0000","N_TIPO_IVA":"1","N_IVA_LINHA":".0000","N_VALOR_TOTAL_DESCONTO":".0000","SERIE_ORIGINAL":"","NUMERO_ORIGINAL":"0","IMPOSTO_ALCOOL":".0000","ECOREEE":".0000","ECOEMBAL":".0000","ECOPILHA":".0000","ECOPNEU":".0000","ECOOUTRO":".0000","VLINTROR":".0000","VLIVAOR":".0000","VLTOTDESCOR":".0000","LINHAARRED":"0","MOTIVOISENCAOSAFT":"","QUANTIDADE_RETIFICADA":".0000","LINHA_RETIFICADA":"0","NUMERO_AUTORIZACAO":"","VERSAOCATALOGOS":"","CCUSTO":"","PROCESSO_ITEM":"","PROJETO":""},{"TPDOCUM":"PF","NNUMDOC":"31","NUMLINHA":"8","TPLINHA":"1","ARTIGO":"","DESCR":"MODELO: AC 110-KWD-2620","PRUNIT":"0","ENCARGOS":"0","QUANT":"0","VALOR":".0000","TXDESC":".0000","DESCONTO":"0","IVA":".0000","SERIE":"22","VLMOVORI":".0000","QTDORIG":".0000","ANO":"2022","RUBRICA":"","VLMOVSTK":".0000","DESCVAL":".0000","MOVSTC":"0","SECTOR":"ANS","ARMAZEM":"","DATA":"2022-10-26 00:00:00.000","ORANO":"0","ORDOC":"","ORSERIE":"","ORNUM":"0","ORLIN":"0","UNIDADE":"","FACTOR":"1.0000","LINANU":"0","TPOPER":"0","DESCVO":".0000","VALORO":".0000","FORMUL":"0","CODLOT":"","ORDENACA":"8","LINHAREL":"0","DESCRRTF":"","ORDGER":"0","IMPRIME":"0","IDLINDOC":"48352","OPERNEW":"MICKAEL","DATENEW":"2022-10-26 00:00:00.000","HOURNEW":"11:29:08","PROCNEW":"1","OPERUPD":"MICKAEL","DATEUPD":"2022-10-26 00:00:00.000","HOURUPD":"11:29:08","PROCUPD":"1","SIGNATUR":"FFA743EFD3CD4CDB7C8973615077B850","INCOER":"0","ARTIGEAN":"","QTDRES":".0000","QTDRESOR":".0000","RESERVA_OBRA":"","VALOR_SAIDA_STOCK":".0000","VALOR_RETENCAO":".0000","TAXA_RETENCAO":".0000","CATEGORIA_RETENCAO":"0","MOVIMENTA_SO_VALOR":"0","VENDEDOR":"Gen","N_PRECO_LINHA_INTRODUZIDO":"0","N_VALOR_LINHA_INTRODUZIDO":".0000","N_TIPO_IVA":"1","N_IVA_LINHA":".0000","N_VALOR_TOTAL_DESCONTO":".0000","SERIE_ORIGINAL":"","NUMERO_ORIGINAL":"0","IMPOSTO_ALCOOL":".0000","ECOREEE":".0000","ECOEMBAL":".0000","ECOPILHA":".0000","ECOPNEU":".0000","ECOOUTRO":".0000","VLINTROR":".0000","VLIVAOR":".0000","VLTOTDESCOR":".0000","LINHAARRED":"0","MOTIVOISENCAOSAFT":"","QUANTIDADE_RETIFICADA":".0000","LINHA_RETIFICADA":"0","NUMERO_AUTORIZACAO":"","VERSAOCATALOGOS":"","CCUSTO":"","PROCESSO_ITEM":"","PROJETO":""}]